[
  {
    "property": [
      {
        "id": "7b423f59-cb8b-4914-b50f-deb8a85d20db",
        "name": "Sunset Villa",
        "address": "123 Main Street",
        "price": 15588,
        "status": "Available",
        "created_at": "2023-09-06T22:16:53.954Z",
        "updated_at": "2023-09-06T15:02:51.661Z",
        "user_id": "user_entity_pk"
      },
      {
        "id": "216a58c8-b80f-4b75-93fc-93a0d9ff0f0d",
        "name": "Greenwood House",
        "address": "456 Elm Avenue",
        "price": 8405,
        "status": "Rented",
        "created_at": "2023-09-07T07:24:58.388Z",
        "updated_at": "2023-09-06T09:59:50.314Z",
        "user_id": "user_entity_pk"
      },
      {
        "id": "dff0234a-7918-4e29-8522-d6d550f39f40",
        "name": "Ocean View Apartment",
        "address": "789 Oak Lane",
        "price": 59029,
        "status": "Under Maintenance",
        "created_at": "2023-09-06T11:00:43.983Z",
        "updated_at": "2023-09-06T14:38:15.682Z",
        "user_id": "user_entity_pk"
      },
      {
        "id": "d8eb2e17-8989-4e15-82ba-87988e25c015",
        "name": "Maplewood Cottage",
        "address": "321 Pine Road",
        "price": 55422,
        "status": "For Sale",
        "created_at": "2023-09-07T03:30:13.537Z",
        "updated_at": "2023-09-07T05:22:50.524Z",
        "user_id": "user_entity_pk"
      },
      {
        "id": "3936c14b-f90f-48e6-8e6f-22b34858e1e5",
        "name": "Meadowbrook Mansion",
        "address": "654 Cedar Drive",
        "price": 69280,
        "status": "Occupied",
        "created_at": "2023-09-06T16:05:42.821Z",
        "updated_at": "2023-09-06T13:21:06.382Z",
        "user_id": "user_entity_pk"
      }
    ],
    "inventory": [
      {
        "id": "3d1289cd-816f-46de-ab30-94493bfd4ec7",
        "item_name": "Laptop",
        "quantity": 83732,
        "created_at": "2023-09-06T21:21:08.339Z",
        "updated_at": "2023-09-07T02:42:07.186Z",
        "user_id": "user_entity_pk"
      },
      {
        "id": "eaff9caf-8d56-407c-9785-f713df007d1e",
        "item_name": "Smartphone",
        "quantity": 7847,
        "created_at": "2023-09-07T07:09:11.385Z",
        "updated_at": "2023-09-06T17:36:37.987Z",
        "user_id": "user_entity_pk"
      },
      {
        "id": "72372545-21d5-4eae-a9a8-c13c3824919c",
        "item_name": "Camera",
        "quantity": 50011,
        "created_at": "2023-09-06T20:42:53.741Z",
        "updated_at": "2023-09-06T14:56:32.752Z",
        "user_id": "user_entity_pk"
      },
      {
        "id": "1b61a1c9-bc2b-463d-857c-102603472092",
        "item_name": "Headphones",
        "quantity": 56107,
        "created_at": "2023-09-06T11:22:52.438Z",
        "updated_at": "2023-09-06T11:42:44.733Z",
        "user_id": "user_entity_pk"
      },
      {
        "id": "3fa9972e-cfac-43b3-9141-9de5d858889b",
        "item_name": "Tablet",
        "quantity": 76185,
        "created_at": "2023-09-06T22:16:26.758Z",
        "updated_at": "2023-09-06T23:42:24.991Z",
        "user_id": "user_entity_pk"
      }
    ],
    "employee": [
      {
        "id": "16ab2eb8-bb07-4004-ae58-3279c6504fb8",
        "name": "John Smith",
        "position": "Manager",
        "salary": 28211,
        "created_at": "2023-09-06T18:57:06.228Z",
        "updated_at": "2023-09-06T14:16:50.207Z",
        "user_id": "user_entity_pk"
      },
      {
        "id": "aa5d57ec-23ff-457c-a22a-ef18a7d7be83",
        "name": "Jane Johnson",
        "position": "Supervisor",
        "salary": 91448,
        "created_at": "2023-09-06T14:35:40.359Z",
        "updated_at": "2023-09-07T01:22:10.088Z",
        "user_id": "user_entity_pk"
      },
      {
        "id": "f1c9b7a3-b337-4607-8a6a-360d813e2fe7",
        "name": "Michael Brown",
        "position": "Assistant",
        "salary": 53389,
        "created_at": "2023-09-06T22:30:40.454Z",
        "updated_at": "2023-09-06T20:02:35.129Z",
        "user_id": "user_entity_pk"
      },
      {
        "id": "e51d6c19-8055-4461-9cec-ac656cb06eb6",
        "name": "Sarah Davis",
        "position": "Analyst",
        "salary": 68780,
        "created_at": "2023-09-06T13:35:27.659Z",
        "updated_at": "2023-09-06T12:21:55.405Z",
        "user_id": "user_entity_pk"
      },
      {
        "id": "fa045f9c-f7d1-4681-b730-b0bcdbc3c89d",
        "name": "Robert Wilson",
        "position": "Coordinator",
        "salary": 10848,
        "created_at": "2023-09-07T07:18:58.565Z",
        "updated_at": "2023-09-07T04:04:25.475Z",
        "user_id": "user_entity_pk"
      }
    ],
    "document": [
      {
        "id": "c975503c-0fd5-4586-ba90-8b4b5b5b2381",
        "name": "Contract",
        "status": "Draft",
        "created_at": "2023-09-06T10:38:47.695Z",
        "updated_at": "2023-09-06T20:15:17.555Z",
        "user_id": "user_entity_pk"
      },
      {
        "id": "c4cffef3-77d0-404e-ac84-6e23c6bcb7b6",
        "name": "Invoice",
        "status": "Pending",
        "created_at": "2023-09-06T17:22:49.777Z",
        "updated_at": "2023-09-06T21:36:04.190Z",
        "user_id": "user_entity_pk"
      },
      {
        "id": "3f4b3c1d-b54a-4a14-bc68-c206d31f26d6",
        "name": "Proposal",
        "status": "Approved",
        "created_at": "2023-09-07T09:07:26.574Z",
        "updated_at": "2023-09-06T20:40:55.055Z",
        "user_id": "user_entity_pk"
      },
      {
        "id": "f85391af-832a-498c-bdc3-86bb4d70f34e",
        "name": "Agreement",
        "status": "Rejected",
        "created_at": "2023-09-07T00:41:56.861Z",
        "updated_at": "2023-09-07T07:45:28.174Z",
        "user_id": "user_entity_pk"
      },
      {
        "id": "b1f898ef-fc53-4148-a4a7-65ca3bc85096",
        "name": "Report",
        "status": "Completed",
        "created_at": "2023-09-06T10:34:18.711Z",
        "updated_at": "2023-09-06T15:04:38.945Z",
        "user_id": "user_entity_pk"
      }
    ],
    "client": [
      {
        "id": "0f5b45bf-ac2d-47a2-8450-9e70cf75fc11",
        "name": "ABC Company",
        "phone": "123-456-7890",
        "address": "789 Main Street",
        "created_at": "2023-09-07T05:46:44.146Z",
        "updated_at": "2023-09-07T02:58:53.014Z",
        "user_id": "user_entity_pk"
      },
      {
        "id": "404ffdf6-bf18-495e-8346-f86df3dd7fd2",
        "name": "XYZ Corporation",
        "phone": "987-654-3210",
        "address": "456 Elm Avenue",
        "created_at": "2023-09-07T08:07:20.611Z",
        "updated_at": "2023-09-06T23:24:16.672Z",
        "user_id": "user_entity_pk"
      },
      {
        "id": "0d89120d-de0f-4057-8c79-3cbd9112b958",
        "name": "123 Enterprises",
        "phone": "555-123-4567",
        "address": "321 Oak Lane",
        "created_at": "2023-09-06T21:47:45.552Z",
        "updated_at": "2023-09-07T07:31:22.728Z",
        "user_id": "user_entity_pk"
      },
      {
        "id": "2afc742d-7582-4196-8fc2-81817d3fe45c",
        "name": "Acme Inc.",
        "phone": "888-999-0000",
        "address": "654 Pine Road",
        "created_at": "2023-09-07T00:59:50.132Z",
        "updated_at": "2023-09-06T16:49:09.822Z",
        "user_id": "user_entity_pk"
      },
      {
        "id": "6424322b-5e14-4207-a386-646064e45be7",
        "name": "Global Solutions",
        "phone": "777-888-9999",
        "address": "987 Cedar Drive",
        "created_at": "2023-09-06T19:10:58.804Z",
        "updated_at": "2023-09-07T07:22:35.852Z",
        "user_id": "user_entity_pk"
      }
    ],
    "roqUser": [
      {
        "reference": "c493dd00-a532-4239-b425-939328950e04",
        "email": "Leann.Okuneva95@gmail.com",
        "firstName": "Chandler",
        "lastName": "Weimann",
        "active": true,
        "avatarUrl": "https://cloudflare-ipfs.com/ipfs/Qmd3W5DuhgHirLHGVixi6V76LhCkZUz6pnFt5AJBiyvHye/avatar/107.jpg",
        "tenantId": null
      },
      {
        "reference": "9c1016ad-87de-4e60-a372-2f8c64b6675c",
        "email": "Albertha12@gmail.com",
        "firstName": "Weldon",
        "lastName": "Wolff",
        "active": true,
        "avatarUrl": "https://cloudflare-ipfs.com/ipfs/Qmd3W5DuhgHirLHGVixi6V76LhCkZUz6pnFt5AJBiyvHye/avatar/648.jpg",
        "tenantId": null
      },
      {
        "reference": "7045f21c-81ba-44fb-abb0-9e4ee9910b94",
        "email": "Dane.Beer88@gmail.com",
        "firstName": "Jaron",
        "lastName": "Graham",
        "active": true,
        "avatarUrl": "https://cloudflare-ipfs.com/ipfs/Qmd3W5DuhgHirLHGVixi6V76LhCkZUz6pnFt5AJBiyvHye/avatar/203.jpg",
        "tenantId": null
      },
      {
        "reference": "368ae03e-7341-4922-8a6e-02fab18cc338",
        "email": "Theresia74@gmail.com",
        "firstName": "Matilda",
        "lastName": "Greenfelder",
        "active": true,
        "avatarUrl": "https://cloudflare-ipfs.com/ipfs/Qmd3W5DuhgHirLHGVixi6V76LhCkZUz6pnFt5AJBiyvHye/avatar/944.jpg",
        "tenantId": null
      },
      {
        "reference": "5d729e03-cbdb-4b74-a699-c1066b1cddb1",
        "email": "Ashleigh75@hotmail.com",
        "firstName": "Adelle",
        "lastName": "Walter",
        "active": true,
        "avatarUrl": "https://cloudflare-ipfs.com/ipfs/Qmd3W5DuhgHirLHGVixi6V76LhCkZUz6pnFt5AJBiyvHye/avatar/1112.jpg",
        "tenantId": null
      }
    ]
  },
  {
    "property": [
      {
        "id": "cf5fadc8-c8c1-43b8-8468-15a832ccd90e",
        "name": "Cozy Cottage",
        "address": "123 Main Street",
        "price": 73375,
        "status": "Available",
        "created_at": "2023-09-06T23:25:21.570Z",
        "updated_at": "2023-09-06T18:35:10.296Z",
        "user_id": "user_entity_pk"
      },
      {
        "id": "85e0cccc-266d-4dd1-80de-55ab48d105a8",
        "name": "Modern Loft",
        "address": "456 Elm Avenue",
        "price": 13787,
        "status": "Rented",
        "created_at": "2023-09-07T08:11:37.900Z",
        "updated_at": "2023-09-07T01:56:31.528Z",
        "user_id": "user_entity_pk"
      },
      {
        "id": "68780061-f507-4226-9efb-151fa9e581d8",
        "name": "Rustic Cabin",
        "address": "789 Oak Lane",
        "price": 87263,
        "status": "Under Maintenance",
        "created_at": "2023-09-06T23:19:18.121Z",
        "updated_at": "2023-09-06T12:05:08.295Z",
        "user_id": "user_entity_pk"
      },
      {
        "id": "977972e1-38d2-4bd2-8943-c1694ecdd03f",
        "name": "Seaside Villa",
        "address": "321 Pine Road",
        "price": 7699,
        "status": "For Sale",
        "created_at": "2023-09-06T18:33:44.043Z",
        "updated_at": "2023-09-06T20:29:22.651Z",
        "user_id": "user_entity_pk"
      },
      {
        "id": "7cb33d68-10d6-44c0-9c44-871500f0234b",
        "name": "Mountain Retreat",
        "address": "654 Maple Court",
        "price": 78608,
        "status": "Occupied",
        "created_at": "2023-09-06T09:25:59.534Z",
        "updated_at": "2023-09-07T00:35:13.988Z",
        "user_id": "user_entity_pk"
      }
    ],
    "inventory": [
      {
        "id": "b8d02e5e-621c-4254-ab77-177760e2c038",
        "item_name": "Smartphone",
        "quantity": 97687,
        "created_at": "2023-09-07T00:37:16.029Z",
        "updated_at": "2023-09-07T03:47:25.356Z",
        "user_id": "user_entity_pk"
      },
      {
        "id": "11b0d33a-e53f-4981-8ae0-57078510d825",
        "item_name": "Laptop",
        "quantity": 48279,
        "created_at": "2023-09-06T17:37:14.502Z",
        "updated_at": "2023-09-07T06:39:46.868Z",
        "user_id": "user_entity_pk"
      },
      {
        "id": "9e81575d-0d49-4e03-88b3-1bb922e57924",
        "item_name": "Camera",
        "quantity": 14273,
        "created_at": "2023-09-06T21:20:48.948Z",
        "updated_at": "2023-09-06T13:31:49.873Z",
        "user_id": "user_entity_pk"
      },
      {
        "id": "1c293eca-d4e3-43fc-9a03-bce3028fd63c",
        "item_name": "Headphones",
        "quantity": 97671,
        "created_at": "2023-09-06T21:18:20.129Z",
        "updated_at": "2023-09-06T23:26:40.203Z",
        "user_id": "user_entity_pk"
      },
      {
        "id": "459c8805-29c4-43d6-b47b-267f967f84fb",
        "item_name": "Smartwatch",
        "quantity": 7529,
        "created_at": "2023-09-06T16:32:31.896Z",
        "updated_at": "2023-09-06T18:10:29.715Z",
        "user_id": "user_entity_pk"
      }
    ],
    "employee": [
      {
        "id": "4318a95c-8542-4eb4-b34d-a6d69fa214ad",
        "name": "John Smith",
        "position": "Manager",
        "salary": 71923,
        "created_at": "2023-09-07T01:31:57.572Z",
        "updated_at": "2023-09-06T12:32:59.234Z",
        "user_id": "user_entity_pk"
      },
      {
        "id": "31e51257-883e-4588-9037-118505d8af1f",
        "name": "Jane Johnson",
        "position": "Supervisor",
        "salary": 87040,
        "created_at": "2023-09-06T12:15:58.988Z",
        "updated_at": "2023-09-07T05:41:31.716Z",
        "user_id": "user_entity_pk"
      },
      {
        "id": "dcfdf370-9843-482a-bb12-e0233e5993c7",
        "name": "Michael Davis",
        "position": "Engineer",
        "salary": 70469,
        "created_at": "2023-09-07T08:56:19.782Z",
        "updated_at": "2023-09-07T08:36:04.578Z",
        "user_id": "user_entity_pk"
      },
      {
        "id": "f00e6042-d6b8-4c48-81d6-8929f13b2d69",
        "name": "Sarah Wilson",
        "position": "Analyst",
        "salary": 86430,
        "created_at": "2023-09-07T00:23:23.579Z",
        "updated_at": "2023-09-07T08:17:39.933Z",
        "user_id": "user_entity_pk"
      },
      {
        "id": "81e2773e-664e-4413-b39e-c5bcdc57232e",
        "name": "David Brown",
        "position": "Assistant",
        "salary": 10401,
        "created_at": "2023-09-07T05:17:41.971Z",
        "updated_at": "2023-09-06T18:06:09.690Z",
        "user_id": "user_entity_pk"
      }
    ],
    "document": [
      {
        "id": "62ed054b-23f0-4643-81d5-411aaeb6decf",
        "name": "Contract Agreement",
        "status": "Draft",
        "created_at": "2023-09-07T02:20:31.104Z",
        "updated_at": "2023-09-07T02:22:38.133Z",
        "user_id": "user_entity_pk"
      },
      {
        "id": "a1f63020-fa7f-4835-8028-bab9c52c8661",
        "name": "Financial Report",
        "status": "Under Review",
        "created_at": "2023-09-06T11:46:10.630Z",
        "updated_at": "2023-09-07T08:03:34.425Z",
        "user_id": "user_entity_pk"
      },
      {
        "id": "da7fa3c0-1650-463a-8630-02b607bde1a7",
        "name": "Project Proposal",
        "status": "Approved",
        "created_at": "2023-09-06T12:34:26.167Z",
        "updated_at": "2023-09-06T15:06:02.742Z",
        "user_id": "user_entity_pk"
      },
      {
        "id": "8515f449-e2eb-486e-80e5-23e44ebdd2d4",
        "name": "Meeting Minutes",
        "status": "Finalized",
        "created_at": "2023-09-06T21:14:40.918Z",
        "updated_at": "2023-09-06T15:42:46.894Z",
        "user_id": "user_entity_pk"
      },
      {
        "id": "dcdf1fa5-8e37-4c7a-9e72-984e36a99485",
        "name": "Training Manual",
        "status": "Archived",
        "created_at": "2023-09-06T11:53:19.432Z",
        "updated_at": "2023-09-06T17:02:15.793Z",
        "user_id": "user_entity_pk"
      }
    ],
    "client": [
      {
        "id": "02d6a2b2-654b-48cd-9ee4-30eb63dfcdfa",
        "name": "ABC Company",
        "phone": "123-456-7890",
        "address": "789 Main Street",
        "created_at": "2023-09-06T14:59:01.370Z",
        "updated_at": "2023-09-06T10:44:41.181Z",
        "user_id": "user_entity_pk"
      },
      {
        "id": "c143f5db-d1b0-4da8-8ad7-9d7af42e9f0c",
        "name": "XYZ Corporation",
        "phone": "555-555-5555",
        "address": "456 Elm Avenue",
        "created_at": "2023-09-06T18:22:30.762Z",
        "updated_at": "2023-09-06T15:41:22.068Z",
        "user_id": "user_entity_pk"
      },
      {
        "id": "6fdfd614-e41b-43a9-87bc-38d577c7f6c0",
        "name": "123 Enterprises",
        "phone": "987-654-3210",
        "address": "123 Oak Lane",
        "created_at": "2023-09-07T06:32:50.006Z",
        "updated_at": "2023-09-07T08:52:41.920Z",
        "user_id": "user_entity_pk"
      },
      {
        "id": "f18afffa-af15-4545-9869-3958f1f92079",
        "name": "Acme Inc.",
        "phone": "888-888-8888",
        "address": "321 Pine Road",
        "created_at": "2023-09-07T08:12:32.910Z",
        "updated_at": "2023-09-06T19:57:55.544Z",
        "user_id": "user_entity_pk"
      },
      {
        "id": "d7aa2238-1735-44f6-b0ff-64bfaa526f4f",
        "name": "Global Solutions",
        "phone": "111-222-3333",
        "address": "654 Maple Court",
        "created_at": "2023-09-06T11:43:06.710Z",
        "updated_at": "2023-09-06T17:57:55.330Z",
        "user_id": "user_entity_pk"
      }
    ],
    "roqUser": [
      {
        "reference": "e0976942-b0c1-4b6f-ac4b-1c2e675282aa",
        "email": "Milford.Paucek@gmail.com",
        "firstName": "Okey",
        "lastName": "Sawayn",
        "active": true,
        "avatarUrl": "https://cloudflare-ipfs.com/ipfs/Qmd3W5DuhgHirLHGVixi6V76LhCkZUz6pnFt5AJBiyvHye/avatar/606.jpg",
        "tenantId": null
      },
      {
        "reference": "7912fdeb-25ac-41a6-99b5-8487e51ddb85",
        "email": "Colt.Nicolas-Hahn@hotmail.com",
        "firstName": "Kristofer",
        "lastName": "Stamm",
        "active": true,
        "avatarUrl": "https://cloudflare-ipfs.com/ipfs/Qmd3W5DuhgHirLHGVixi6V76LhCkZUz6pnFt5AJBiyvHye/avatar/603.jpg",
        "tenantId": null
      },
      {
        "reference": "8997cece-5a38-4658-bf99-da9ea5c0b519",
        "email": "Casimer_Kub@yahoo.com",
        "firstName": "Izabella",
        "lastName": "Berge",
        "active": true,
        "avatarUrl": "https://avatars.githubusercontent.com/u/16139393",
        "tenantId": null
      },
      {
        "reference": "98eb0672-8534-4fc2-ab3d-f29baa3803c3",
        "email": "Katharina26@gmail.com",
        "firstName": "Emiliano",
        "lastName": "Will",
        "active": true,
        "avatarUrl": "https://cloudflare-ipfs.com/ipfs/Qmd3W5DuhgHirLHGVixi6V76LhCkZUz6pnFt5AJBiyvHye/avatar/639.jpg",
        "tenantId": null
      },
      {
        "reference": "c635b0d8-d403-428c-b98f-505e8a7d2641",
        "email": "Aletha_Mante82@gmail.com",
        "firstName": "Dora",
        "lastName": "Barton",
        "active": true,
        "avatarUrl": "https://avatars.githubusercontent.com/u/63311510",
        "tenantId": null
      }
    ]
  },
  {
    "property": [
      {
        "id": "d679ac2a-958a-4325-a672-762fbeeb1e48",
        "name": "Ocean View Villa",
        "address": "123 Main Street",
        "price": 10369,
        "status": "Available",
        "created_at": "2023-09-07T00:26:37.035Z",
        "updated_at": "2023-09-07T09:03:50.939Z",
        "user_id": "user_entity_pk"
      },
      {
        "id": "f822a6b2-fe0f-47f9-b748-d3ac98ce2742",
        "name": "Mountain Retreat",
        "address": "456 Elm Avenue",
        "price": 76717,
        "status": "Rented",
        "created_at": "2023-09-06T22:33:14.716Z",
        "updated_at": "2023-09-06T22:54:39.776Z",
        "user_id": "user_entity_pk"
      },
      {
        "id": "4b0fb2b9-0afd-47a9-886d-77e373d6856e",
        "name": "City Condo",
        "address": "789 Oak Drive",
        "price": 31795,
        "status": "Under Renovation",
        "created_at": "2023-09-06T12:50:28.825Z",
        "updated_at": "2023-09-07T07:07:48.709Z",
        "user_id": "user_entity_pk"
      },
      {
        "id": "3cd65a9f-d29e-4290-9260-7b4b35cc954c",
        "name": "Lake House",
        "address": "321 Pine Lane",
        "price": 48493,
        "status": "For Sale",
        "created_at": "2023-09-07T04:01:25.638Z",
        "updated_at": "2023-09-07T07:26:29.236Z",
        "user_id": "user_entity_pk"
      },
      {
        "id": "1d82b961-2e6a-4e71-8ef6-87a6cf17cd54",
        "name": "Country Estate",
        "address": "654 Cedar Road",
        "price": 36549,
        "status": "Sold",
        "created_at": "2023-09-06T15:55:45.602Z",
        "updated_at": "2023-09-07T04:56:30.995Z",
        "user_id": "user_entity_pk"
      }
    ],
    "inventory": [
      {
        "id": "9eace756-123f-4da6-8187-bb70ee7c07d9",
        "item_name": "Smartphone",
        "quantity": 22283,
        "created_at": "2023-09-06T19:40:14.492Z",
        "updated_at": "2023-09-07T04:45:56.881Z",
        "user_id": "user_entity_pk"
      },
      {
        "id": "bc390972-c7ca-4991-a57d-34b4ad22687f",
        "item_name": "Laptop",
        "quantity": 88399,
        "created_at": "2023-09-06T13:02:46.175Z",
        "updated_at": "2023-09-06T22:33:18.865Z",
        "user_id": "user_entity_pk"
      },
      {
        "id": "b38d8998-16c5-4927-8671-fd3355eb35bc",
        "item_name": "Headphones",
        "quantity": 88158,
        "created_at": "2023-09-06T17:01:12.657Z",
        "updated_at": "2023-09-06T12:07:04.913Z",
        "user_id": "user_entity_pk"
      },
      {
        "id": "f324cf88-ebb4-43b6-9c01-ba62e9921f46",
        "item_name": "Camera",
        "quantity": 26887,
        "created_at": "2023-09-07T02:56:10.883Z",
        "updated_at": "2023-09-07T04:48:48.221Z",
        "user_id": "user_entity_pk"
      },
      {
        "id": "6649e94a-4daf-4d6b-8ecf-ecac75ef8e47",
        "item_name": "Smartwatch",
        "quantity": 59803,
        "created_at": "2023-09-06T16:34:40.617Z",
        "updated_at": "2023-09-06T17:36:23.184Z",
        "user_id": "user_entity_pk"
      }
    ],
    "employee": [
      {
        "id": "57056ebc-2f0c-444b-9e27-37e30e97b24f",
        "name": "John Smith",
        "position": "Manager",
        "salary": 95728,
        "created_at": "2023-09-06T11:51:39.701Z",
        "updated_at": "2023-09-07T07:58:39.481Z",
        "user_id": "user_entity_pk"
      },
      {
        "id": "240655ca-a7fb-47b0-886a-f9a5ad06f075",
        "name": "Jane Doe",
        "position": "Engineer",
        "salary": 7475,
        "created_at": "2023-09-06T20:20:00.727Z",
        "updated_at": "2023-09-07T06:37:53.052Z",
        "user_id": "user_entity_pk"
      },
      {
        "id": "1daad7f8-e8f3-4ee6-a24f-18106c96b5f3",
        "name": "Michael Brown",
        "position": "Sales Representative",
        "salary": 18652,
        "created_at": "2023-09-07T09:07:35.190Z",
        "updated_at": "2023-09-07T00:05:01.746Z",
        "user_id": "user_entity_pk"
      },
      {
        "id": "012a2168-f11e-4a7d-bcc6-420eb3697df3",
        "name": "Sarah Wilson",
        "position": "Designer",
        "salary": 83199,
        "created_at": "2023-09-06T14:47:25.129Z",
        "updated_at": "2023-09-06T20:34:33.337Z",
        "user_id": "user_entity_pk"
      },
      {
        "id": "cca01a33-949c-4548-b715-e34ef511348f",
        "name": "David Johnson",
        "position": "Accountant",
        "salary": 70108,
        "created_at": "2023-09-07T00:03:13.734Z",
        "updated_at": "2023-09-06T14:37:55.931Z",
        "user_id": "user_entity_pk"
      }
    ],
    "document": [
      {
        "id": "b95613d6-2b3a-4daf-b275-3b33a2d48f71",
        "name": "Contract",
        "status": "Draft",
        "created_at": "2023-09-06T11:57:53.770Z",
        "updated_at": "2023-09-06T21:14:55.566Z",
        "user_id": "user_entity_pk"
      },
      {
        "id": "16f66134-8a52-46ad-a9af-6e5e0a518fe5",
        "name": "Invoice",
        "status": "Pending",
        "created_at": "2023-09-07T01:45:05.980Z",
        "updated_at": "2023-09-07T06:25:09.688Z",
        "user_id": "user_entity_pk"
      },
      {
        "id": "9541aa8c-1235-4bfb-83f5-bbe254a28634",
        "name": "Report",
        "status": "Approved",
        "created_at": "2023-09-06T15:42:37.640Z",
        "updated_at": "2023-09-06T21:43:56.275Z",
        "user_id": "user_entity_pk"
      },
      {
        "id": "0e2ea479-dec1-4ac1-9b73-d5fbffe67924",
        "name": "Proposal",
        "status": "Rejected",
        "created_at": "2023-09-07T08:37:03.064Z",
        "updated_at": "2023-09-06T11:46:10.199Z",
        "user_id": "user_entity_pk"
      },
      {
        "id": "eae4b18e-08f5-4068-b173-21150e3ff00c",
        "name": "Agreement",
        "status": "Finalized",
        "created_at": "2023-09-06T15:31:53.060Z",
        "updated_at": "2023-09-07T05:43:02.534Z",
        "user_id": "user_entity_pk"
      }
    ],
    "client": [
      {
        "id": "1e032668-2d9a-4c3d-be44-10b6e77730cb",
        "name": "ABC Company",
        "phone": "123-456-7890",
        "address": "123 Main Street",
        "created_at": "2023-09-06T13:50:14.257Z",
        "updated_at": "2023-09-06T22:52:44.864Z",
        "user_id": "user_entity_pk"
      },
      {
        "id": "4d5bed8d-7dbd-44d0-97e5-1a7222ae4b59",
        "name": "XYZ Corporation",
        "phone": "555-555-5555",
        "address": "456 Elm Avenue",
        "created_at": "2023-09-07T02:39:09.443Z",
        "updated_at": "2023-09-06T16:26:45.994Z",
        "user_id": "user_entity_pk"
      },
      {
        "id": "bb3b560d-5848-4805-a636-77fbbea66bf6",
        "name": "123 Enterprises",
        "phone": "987-654-3210",
        "address": "789 Oak Drive",
        "created_at": "2023-09-06T23:32:15.407Z",
        "updated_at": "2023-09-06T17:13:40.128Z",
        "user_id": "user_entity_pk"
      },
      {
        "id": "37dd14b6-669b-4029-a267-4c22fd8a949e",
        "name": "Acme Inc.",
        "phone": "888-888-8888",
        "address": "321 Pine Lane",
        "created_at": "2023-09-06T16:48:01.865Z",
        "updated_at": "2023-09-06T14:49:05.078Z",
        "user_id": "user_entity_pk"
      },
      {
        "id": "ec5a9e04-f10c-4a8b-bf68-753f1b4484db",
        "name": "Global Solutions",
        "phone": "111-222-3333",
        "address": "654 Cedar Road",
        "created_at": "2023-09-06T15:58:38.903Z",
        "updated_at": "2023-09-07T05:24:48.313Z",
        "user_id": "user_entity_pk"
      }
    ],
    "roqUser": [
      {
        "reference": "a7202c5e-873d-495a-b1d3-517ead229b0d",
        "email": "Lon50@yahoo.com",
        "firstName": "Santina",
        "lastName": "Miller",
        "active": true,
        "avatarUrl": "https://avatars.githubusercontent.com/u/37296219",
        "tenantId": null
      },
      {
        "reference": "eff843db-7929-4250-8448-287537dbb4d9",
        "email": "Chaim16@gmail.com",
        "firstName": "Andres",
        "lastName": "Harvey-Gibson",
        "active": true,
        "avatarUrl": "https://avatars.githubusercontent.com/u/59855020",
        "tenantId": null
      },
      {
        "reference": "3e56a920-8af0-40c4-89d0-a1b0d51d2fc1",
        "email": "Alivia_Ankunding44@yahoo.com",
        "firstName": "Pete",
        "lastName": "Funk",
        "active": true,
        "avatarUrl": "https://avatars.githubusercontent.com/u/99240914",
        "tenantId": null
      },
      {
        "reference": "b52b3ebf-8bf9-4380-ab0d-29aa354b6bea",
        "email": "Aylin79@hotmail.com",
        "firstName": "Tessie",
        "lastName": "Fay",
        "active": true,
        "avatarUrl": "https://cloudflare-ipfs.com/ipfs/Qmd3W5DuhgHirLHGVixi6V76LhCkZUz6pnFt5AJBiyvHye/avatar/502.jpg",
        "tenantId": null
      },
      {
        "reference": "577a57da-77a0-4f47-8a5b-61f9dc52980a",
        "email": "Breanna.Kerluke@yahoo.com",
        "firstName": "Mercedes",
        "lastName": "Pfannerstill",
        "active": true,
        "avatarUrl": "https://avatars.githubusercontent.com/u/44216687",
        "tenantId": null
      }
    ]
  },
  {
    "property": [
      {
        "id": "9d60c28a-4408-4f5d-990e-cd8fda2be74e",
        "name": "Villa Sunshine",
        "address": "123 Main Street",
        "price": 31273,
        "status": "Available",
        "created_at": "2023-09-06T19:01:21.463Z",
        "updated_at": "2023-09-06T10:15:48.456Z",
        "user_id": "user_entity_pk"
      },
      {
        "id": "80f66fce-eec1-4949-b0e7-79fd27688036",
        "name": "Ocean View Apartment",
        "address": "456 Elm Avenue",
        "price": 94474,
        "status": "Occupied",
        "created_at": "2023-09-06T20:50:56.313Z",
        "updated_at": "2023-09-07T02:01:04.851Z",
        "user_id": "user_entity_pk"
      },
      {
        "id": "7dede1e3-e816-457f-954f-6e80f98fb932",
        "name": "Mountain Retreat",
        "address": "789 Oak Drive",
        "price": 17891,
        "status": "Under Renovation",
        "created_at": "2023-09-06T10:48:19.453Z",
        "updated_at": "2023-09-06T15:32:12.712Z",
        "user_id": "user_entity_pk"
      },
      {
        "id": "336e5a78-050e-46c0-ba95-1c85eae05d1c",
        "name": "City Loft",
        "address": "321 Pine Lane",
        "price": 66268,
        "status": "For Sale",
        "created_at": "2023-09-06T10:29:19.186Z",
        "updated_at": "2023-09-06T18:18:49.721Z",
        "user_id": "user_entity_pk"
      },
      {
        "id": "3581bac7-fd14-4294-b9e3-6be7295dc1b8",
        "name": "Lakefront Cottage",
        "address": "654 Maple Road",
        "price": 80704,
        "status": "Pending Approval",
        "created_at": "2023-09-07T03:49:41.203Z",
        "updated_at": "2023-09-06T20:57:06.616Z",
        "user_id": "user_entity_pk"
      }
    ],
    "inventory": [
      {
        "id": "1a06be5f-4bca-4e4d-9815-8ee3485b5ce8",
        "item_name": "Smartphone",
        "quantity": 31424,
        "created_at": "2023-09-06T11:07:57.782Z",
        "updated_at": "2023-09-06T09:31:00.075Z",
        "user_id": "user_entity_pk"
      },
      {
        "id": "33e8a8a0-cb53-49ad-9630-d53ba666bded",
        "item_name": "Laptop",
        "quantity": 95377,
        "created_at": "2023-09-06T22:37:03.496Z",
        "updated_at": "2023-09-07T07:46:50.280Z",
        "user_id": "user_entity_pk"
      },
      {
        "id": "07daf14d-95f3-49d9-ad42-0c1e0e9116ea",
        "item_name": "Camera",
        "quantity": 36814,
        "created_at": "2023-09-07T00:58:31.430Z",
        "updated_at": "2023-09-06T09:39:24.527Z",
        "user_id": "user_entity_pk"
      },
      {
        "id": "3281d750-f05b-49d9-9045-121bb406f8fa",
        "item_name": "Headphones",
        "quantity": 87237,
        "created_at": "2023-09-06T10:28:06.459Z",
        "updated_at": "2023-09-06T21:29:53.782Z",
        "user_id": "user_entity_pk"
      },
      {
        "id": "0b03e862-416b-4208-b9ec-6a31a8f38fe7",
        "item_name": "Smartwatch",
        "quantity": 17205,
        "created_at": "2023-09-07T05:06:31.695Z",
        "updated_at": "2023-09-06T13:59:49.222Z",
        "user_id": "user_entity_pk"
      }
    ],
    "employee": [
      {
        "id": "7b997f61-c05d-4418-bd08-60a3943cbee1",
        "name": "John Smith",
        "position": "Manager",
        "salary": 75079,
        "created_at": "2023-09-06T13:02:22.017Z",
        "updated_at": "2023-09-06T14:55:46.188Z",
        "user_id": "user_entity_pk"
      },
      {
        "id": "c454b366-b1ab-427f-8886-ccb868bc9e2d",
        "name": "Emily Johnson",
        "position": "Sales Associate",
        "salary": 29144,
        "created_at": "2023-09-06T10:24:01.507Z",
        "updated_at": "2023-09-07T07:03:58.785Z",
        "user_id": "user_entity_pk"
      },
      {
        "id": "cdcad493-c9dd-48cf-a388-096182e171c3",
        "name": "Michael Brown",
        "position": "Software Engineer",
        "salary": 53458,
        "created_at": "2023-09-06T16:53:12.902Z",
        "updated_at": "2023-09-07T00:26:01.664Z",
        "user_id": "user_entity_pk"
      },
      {
        "id": "86c01265-5506-41f6-bfa1-305720956612",
        "name": "Jessica Wilson",
        "position": "HR Specialist",
        "salary": 44182,
        "created_at": "2023-09-07T02:25:22.398Z",
        "updated_at": "2023-09-06T12:13:40.150Z",
        "user_id": "user_entity_pk"
      },
      {
        "id": "9219eba4-40b6-47f7-9ac5-e94fb237a913",
        "name": "David Davis",
        "position": "Accountant",
        "salary": 84567,
        "created_at": "2023-09-07T06:01:15.419Z",
        "updated_at": "2023-09-07T08:06:29.628Z",
        "user_id": "user_entity_pk"
      }
    ],
    "document": [
      {
        "id": "e524fff7-ac74-45b2-8630-4f6984685b76",
        "name": "Contract",
        "status": "Draft",
        "created_at": "2023-09-07T08:58:31.563Z",
        "updated_at": "2023-09-07T04:32:08.710Z",
        "user_id": "user_entity_pk"
      },
      {
        "id": "d799edc6-f8a7-4ac2-8124-15ab1313664b",
        "name": "Invoice",
        "status": "Pending",
        "created_at": "2023-09-07T05:24:05.911Z",
        "updated_at": "2023-09-07T07:53:44.593Z",
        "user_id": "user_entity_pk"
      },
      {
        "id": "f4c2c011-e2f5-4f49-adcc-7013f6c64e2d",
        "name": "Report",
        "status": "Approved",
        "created_at": "2023-09-07T08:12:23.750Z",
        "updated_at": "2023-09-07T06:13:44.302Z",
        "user_id": "user_entity_pk"
      },
      {
        "id": "09ba16eb-d380-49cb-9141-919dae3cabcd",
        "name": "Proposal",
        "status": "Rejected",
        "created_at": "2023-09-06T15:49:14.175Z",
        "updated_at": "2023-09-07T06:35:26.704Z",
        "user_id": "user_entity_pk"
      },
      {
        "id": "fddd882b-2358-482d-9fee-34efbbbb9b82",
        "name": "Agreement",
        "status": "Finalized",
        "created_at": "2023-09-06T18:07:11.357Z",
        "updated_at": "2023-09-07T08:59:14.441Z",
        "user_id": "user_entity_pk"
      }
    ],
    "client": [
      {
        "id": "82dcf42b-5266-4570-a009-8f2d05b80d50",
        "name": "ABC Company",
        "phone": "123-456-7890",
        "address": "789 Main Street",
        "created_at": "2023-09-06T12:24:47.763Z",
        "updated_at": "2023-09-06T23:58:48.178Z",
        "user_id": "user_entity_pk"
      },
      {
        "id": "62c3bdee-7d76-4a7b-9b59-b1d388f7707f",
        "name": "XYZ Corporation",
        "phone": "987-654-3210",
        "address": "456 Elm Avenue",
        "created_at": "2023-09-06T22:47:18.444Z",
        "updated_at": "2023-09-06T17:00:52.863Z",
        "user_id": "user_entity_pk"
      },
      {
        "id": "5dd04286-db37-4ce0-b9c2-1f2c0b4d945e",
        "name": "123 Enterprises",
        "phone": "555-123-4567",
        "address": "123 Oak Drive",
        "created_at": "2023-09-06T17:28:27.248Z",
        "updated_at": "2023-09-07T04:33:34.160Z",
        "user_id": "user_entity_pk"
      },
      {
        "id": "d2ffdfd6-5fb1-432b-bd32-92a0ccd8de4d",
        "name": "Acme Inc.",
        "phone": "888-999-0000",
        "address": "321 Pine Lane",
        "created_at": "2023-09-06T20:20:22.928Z",
        "updated_at": "2023-09-07T05:55:48.882Z",
        "user_id": "user_entity_pk"
      },
      {
        "id": "ccbbe534-bd74-42e4-b7a6-8450135efdc3",
        "name": "Global Solutions",
        "phone": "444-555-6666",
        "address": "654 Maple Road",
        "created_at": "2023-09-07T07:33:27.481Z",
        "updated_at": "2023-09-06T20:12:32.038Z",
        "user_id": "user_entity_pk"
      }
    ],
    "roqUser": [
      {
        "reference": "2f046749-e2d4-40ac-a9e7-14873e6656b2",
        "email": "Perry_Pfeffer14@gmail.com",
        "firstName": "Johnnie",
        "lastName": "Schuppe",
        "active": true,
        "avatarUrl": "https://cloudflare-ipfs.com/ipfs/Qmd3W5DuhgHirLHGVixi6V76LhCkZUz6pnFt5AJBiyvHye/avatar/463.jpg",
        "tenantId": null
      },
      {
        "reference": "07e7b3d4-4c7a-43c7-9aa8-17f533e8e148",
        "email": "Veda27@hotmail.com",
        "firstName": "Joany",
        "lastName": "Kulas",
        "active": true,
        "avatarUrl": "https://avatars.githubusercontent.com/u/99772450",
        "tenantId": null
      },
      {
        "reference": "a8dba8fc-aa88-40cc-b027-eb411433518d",
        "email": "Osbaldo6@yahoo.com",
        "firstName": "Shanon",
        "lastName": "Schoen",
        "active": true,
        "avatarUrl": "https://avatars.githubusercontent.com/u/5766396",
        "tenantId": null
      },
      {
        "reference": "5e28e58f-06f0-4478-805a-d9b88e14f725",
        "email": "Keyshawn.Leannon@gmail.com",
        "firstName": "Nayeli",
        "lastName": "O'Keefe",
        "active": true,
        "avatarUrl": "https://cloudflare-ipfs.com/ipfs/Qmd3W5DuhgHirLHGVixi6V76LhCkZUz6pnFt5AJBiyvHye/avatar/1240.jpg",
        "tenantId": null
      },
      {
        "reference": "0d5b6f6b-d21d-4610-b3bd-7f7ce926034c",
        "email": "Juwan_McClure90@yahoo.com",
        "firstName": "Darron",
        "lastName": "Gleichner",
        "active": true,
        "avatarUrl": "https://avatars.githubusercontent.com/u/67468109",
        "tenantId": null
      }
    ]
  },
  {
    "property": [
      {
        "id": "7f882e74-d4d7-4dea-b12b-20e727ad1132",
        "name": "Cozy Cottage",
        "address": "123 Main St",
        "price": 81802,
        "status": "Available",
        "created_at": "2023-09-07T01:56:07.943Z",
        "updated_at": "2023-09-06T16:52:36.921Z",
        "user_id": "user_entity_pk"
      },
      {
        "id": "a963f45e-8971-4dcf-8489-cf23a84190c4",
        "name": "Sunny Villa",
        "address": "456 Elm St",
        "price": 50993,
        "status": "Booked",
        "created_at": "2023-09-07T07:59:07.247Z",
        "updated_at": "2023-09-06T22:31:48.652Z",
        "user_id": "user_entity_pk"
      },
      {
        "id": "6750ae7c-9f44-4141-8ade-c3b1b242ea81",
        "name": "Rustic Cabin",
        "address": "789 Oak Ave",
        "price": 90718,
        "status": "Under Maintenance",
        "created_at": "2023-09-06T20:13:41.218Z",
        "updated_at": "2023-09-06T17:18:38.951Z",
        "user_id": "user_entity_pk"
      },
      {
        "id": "2104a111-742a-431a-a228-f3e3b73a036c",
        "name": "Modern Loft",
        "address": "321 Pine Rd",
        "price": 18443,
        "status": "Sold",
        "created_at": "2023-09-07T02:26:55.627Z",
        "updated_at": "2023-09-06T18:09:11.083Z",
        "user_id": "user_entity_pk"
      },
      {
        "id": "b3ccd6bf-f3c3-4580-942a-03f133cc0d7e",
        "name": "Seaside Retreat",
        "address": "654 Maple Ln",
        "price": 69008,
        "status": "Vacant",
        "created_at": "2023-09-07T02:04:13.757Z",
        "updated_at": "2023-09-06T16:21:05.215Z",
        "user_id": "user_entity_pk"
      }
    ],
    "inventory": [
      {
        "id": "d2095a66-274f-4c58-9fc6-181328756d3b",
        "item_name": "Laptop",
        "quantity": 96720,
        "created_at": "2023-09-06T22:09:21.549Z",
        "updated_at": "2023-09-06T17:02:03.595Z",
        "user_id": "user_entity_pk"
      },
      {
        "id": "3caa4a00-6da3-464b-8ddf-2901d6891f1b",
        "item_name": "Smartphone",
        "quantity": 25842,
        "created_at": "2023-09-07T07:19:08.344Z",
        "updated_at": "2023-09-06T15:13:13.590Z",
        "user_id": "user_entity_pk"
      },
      {
        "id": "54cde0c4-ca2e-417c-a3b1-c7f53d89aed2",
        "item_name": "Camera",
        "quantity": 69985,
        "created_at": "2023-09-07T00:14:52.632Z",
        "updated_at": "2023-09-06T10:58:37.383Z",
        "user_id": "user_entity_pk"
      },
      {
        "id": "4616b739-6b64-4596-b39d-1d0a448f6537",
        "item_name": "Headphones",
        "quantity": 6020,
        "created_at": "2023-09-07T04:11:05.486Z",
        "updated_at": "2023-09-06T16:03:42.975Z",
        "user_id": "user_entity_pk"
      },
      {
        "id": "9ab8f7b4-8208-4762-ad59-9ac17f58fe2c",
        "item_name": "Tablet",
        "quantity": 85634,
        "created_at": "2023-09-07T06:02:04.108Z",
        "updated_at": "2023-09-06T17:13:38.381Z",
        "user_id": "user_entity_pk"
      }
    ],
    "employee": [
      {
        "id": "e1aa904a-b013-40cd-a81b-a98e6c8e89d0",
        "name": "John Smith",
        "position": "Manager",
        "salary": 26349,
        "created_at": "2023-09-06T15:22:17.843Z",
        "updated_at": "2023-09-06T16:10:21.148Z",
        "user_id": "user_entity_pk"
      },
      {
        "id": "513e33a9-44e9-49f3-855c-d39bf2583455",
        "name": "Jane Doe",
        "position": "Assistant",
        "salary": 16359,
        "created_at": "2023-09-06T22:39:32.231Z",
        "updated_at": "2023-09-07T01:07:39.993Z",
        "user_id": "user_entity_pk"
      },
      {
        "id": "58b02d67-37f7-4886-8823-517a05f8815d",
        "name": "Michael Brown",
        "position": "Supervisor",
        "salary": 96696,
        "created_at": "2023-09-06T17:25:09.378Z",
        "updated_at": "2023-09-06T19:05:09.544Z",
        "user_id": "user_entity_pk"
      },
      {
        "id": "13563cf8-df77-4502-b237-10923a2c5935",
        "name": "Sarah Jones",
        "position": "Coordinator",
        "salary": 48838,
        "created_at": "2023-09-06T17:16:51.626Z",
        "updated_at": "2023-09-06T16:14:16.244Z",
        "user_id": "user_entity_pk"
      },
      {
        "id": "040287f0-c775-4942-b61b-1f7d9ba1938b",
        "name": "David Wilson",
        "position": "Specialist",
        "salary": 46783,
        "created_at": "2023-09-06T15:19:41.762Z",
        "updated_at": "2023-09-07T01:29:08.947Z",
        "user_id": "user_entity_pk"
      }
    ],
    "document": [
      {
        "id": "c3abc9ba-a461-4560-9760-ca695ceb20be",
        "name": "Contract Agreement",
        "status": "Draft",
        "created_at": "2023-09-06T19:48:37.680Z",
        "updated_at": "2023-09-07T06:50:32.737Z",
        "user_id": "user_entity_pk"
      },
      {
        "id": "eeb8e593-65e9-458c-a0e2-24cb18838339",
        "name": "Invoice",
        "status": "Pending",
        "created_at": "2023-09-07T01:09:29.130Z",
        "updated_at": "2023-09-07T05:42:42.142Z",
        "user_id": "user_entity_pk"
      },
      {
        "id": "bc65229b-18f1-4662-ba0a-617747f20f4c",
        "name": "Purchase Order",
        "status": "Approved",
        "created_at": "2023-09-06T12:29:57.328Z",
        "updated_at": "2023-09-06T21:07:13.357Z",
        "user_id": "user_entity_pk"
      },
      {
        "id": "320b5d76-e73e-4467-9eca-63972e0a39a1",
        "name": "Annual Report",
        "status": "Rejected",
        "created_at": "2023-09-06T10:35:33.193Z",
        "updated_at": "2023-09-06T09:36:17.613Z",
        "user_id": "user_entity_pk"
      },
      {
        "id": "dd2daed7-64f3-4dde-aeab-98f91b2cd3ec",
        "name": "Employee Handbook",
        "status": "Finalized",
        "created_at": "2023-09-07T02:02:54.937Z",
        "updated_at": "2023-09-07T03:17:22.937Z",
        "user_id": "user_entity_pk"
      }
    ],
    "client": [
      {
        "id": "caf34d76-7160-4fd4-b6cc-e0d0f2c24b4e",
        "name": "ABC Company",
        "phone": "123-456-7890",
        "address": "456 Main St",
        "created_at": "2023-09-07T08:56:06.170Z",
        "updated_at": "2023-09-07T00:14:31.035Z",
        "user_id": "user_entity_pk"
      },
      {
        "id": "85cb80e2-cbe1-454c-9420-3c624ea3edc6",
        "name": "XYZ Corporation",
        "phone": "987-654-3210",
        "address": "789 Elm St",
        "created_at": "2023-09-06T10:29:10.067Z",
        "updated_at": "2023-09-06T16:31:21.026Z",
        "user_id": "user_entity_pk"
      },
      {
        "id": "69c16346-94a8-4d47-aac1-d7e2b01029e0",
        "name": "123 Enterprises",
        "phone": "555-123-4567",
        "address": "321 Oak Ave",
        "created_at": "2023-09-06T18:00:56.498Z",
        "updated_at": "2023-09-06T10:19:54.116Z",
        "user_id": "user_entity_pk"
      },
      {
        "id": "e9ac8bd0-dda9-414f-97bb-ef5aeae25a08",
        "name": "Acme Inc.",
        "phone": "888-999-0000",
        "address": "654 Pine Rd",
        "created_at": "2023-09-06T13:49:36.488Z",
        "updated_at": "2023-09-06T15:46:02.105Z",
        "user_id": "user_entity_pk"
      },
      {
        "id": "4af3ede3-ae68-4a8b-b866-b36b9b6d18bf",
        "name": "Global Solutions",
        "phone": "777-888-9999",
        "address": "987 Maple Ln",
        "created_at": "2023-09-06T22:55:45.825Z",
        "updated_at": "2023-09-07T09:13:10.683Z",
        "user_id": "user_entity_pk"
      }
    ],
    "roqUser": [
      {
        "reference": "7dc5faad-16d2-454e-a862-8e2512f466aa",
        "email": "Kassandra_Schneider@gmail.com",
        "firstName": "Marjolaine",
        "lastName": "Mueller",
        "active": true,
        "avatarUrl": "https://avatars.githubusercontent.com/u/25481036",
        "tenantId": null
      },
      {
        "reference": "aacd1c5a-fa49-4e24-a781-6ae02831d2f9",
        "email": "Kory36@hotmail.com",
        "firstName": "Tianna",
        "lastName": "Pouros",
        "active": true,
        "avatarUrl": "https://avatars.githubusercontent.com/u/4917248",
        "tenantId": null
      },
      {
        "reference": "47349ccb-3b80-4258-8a4f-5599d3b2f266",
        "email": "Koby80@hotmail.com",
        "firstName": "Enid",
        "lastName": "King",
        "active": true,
        "avatarUrl": "https://cloudflare-ipfs.com/ipfs/Qmd3W5DuhgHirLHGVixi6V76LhCkZUz6pnFt5AJBiyvHye/avatar/1070.jpg",
        "tenantId": null
      },
      {
        "reference": "bee89821-1ce4-4821-95a1-9838e35b90bf",
        "email": "Ettie26@yahoo.com",
        "firstName": "Abdullah",
        "lastName": "Hilpert",
        "active": true,
        "avatarUrl": "https://cloudflare-ipfs.com/ipfs/Qmd3W5DuhgHirLHGVixi6V76LhCkZUz6pnFt5AJBiyvHye/avatar/192.jpg",
        "tenantId": null
      },
      {
        "reference": "4c338a86-78a9-4e17-bba0-a9676ef8ce1a",
        "email": "Frances_Langworth@hotmail.com",
        "firstName": "Terrence",
        "lastName": "Boyle",
        "active": true,
        "avatarUrl": "https://avatars.githubusercontent.com/u/53226494",
        "tenantId": null
      }
    ]
  },
  {
    "property": [
      {
        "id": "c178425a-f085-4968-ac9d-b1bb5d4a18e6",
        "name": "Villa Sunshine",
        "address": "123 Main Street",
        "price": 20079,
        "status": "Available",
        "created_at": "2023-09-07T03:54:57.650Z",
        "updated_at": "2023-09-06T11:31:56.018Z",
        "user_id": "user_entity_pk"
      },
      {
        "id": "d707b5e1-290b-4ab8-8fc3-e63682308576",
        "name": "Ocean View Apartment",
        "address": "456 Elm Avenue",
        "price": 8657,
        "status": "Rented",
        "created_at": "2023-09-07T02:58:44.151Z",
        "updated_at": "2023-09-07T02:56:11.493Z",
        "user_id": "user_entity_pk"
      },
      {
        "id": "b2a588c6-e759-4ea7-8538-07985b1c0b3b",
        "name": "Mountain Retreat",
        "address": "789 Oak Lane",
        "price": 79867,
        "status": "Under Maintenance",
        "created_at": "2023-09-06T12:27:14.021Z",
        "updated_at": "2023-09-06T10:50:37.651Z",
        "user_id": "user_entity_pk"
      },
      {
        "id": "9dd23f26-e66e-40db-9423-be63fbfd6dc5",
        "name": "City Loft",
        "address": "321 Pine Road",
        "price": 12638,
        "status": "Sold",
        "created_at": "2023-09-07T07:06:48.271Z",
        "updated_at": "2023-09-06T19:10:57.811Z",
        "user_id": "user_entity_pk"
      },
      {
        "id": "fb1accf2-a6a4-420a-87ae-8df7e965102e",
        "name": "Beach House",
        "address": "654 Maple Drive",
        "price": 9878,
        "status": "Vacant",
        "created_at": "2023-09-07T07:22:32.730Z",
        "updated_at": "2023-09-07T05:00:43.400Z",
        "user_id": "user_entity_pk"
      }
    ],
    "inventory": [
      {
        "id": "57a98ee7-e864-4080-a22e-8123903d2ce0",
        "item_name": "Smartphone",
        "quantity": 80592,
        "created_at": "2023-09-06T14:15:10.461Z",
        "updated_at": "2023-09-07T00:53:23.904Z",
        "user_id": "user_entity_pk"
      },
      {
        "id": "63839ee8-276c-4067-8983-30ec7e74ac83",
        "item_name": "Laptop",
        "quantity": 37295,
        "created_at": "2023-09-06T13:32:01.977Z",
        "updated_at": "2023-09-07T08:24:32.358Z",
        "user_id": "user_entity_pk"
      },
      {
        "id": "8ed2b2e0-f578-4f3a-af57-160207ac98d7",
        "item_name": "Camera",
        "quantity": 20890,
        "created_at": "2023-09-07T08:27:45.065Z",
        "updated_at": "2023-09-07T06:30:56.326Z",
        "user_id": "user_entity_pk"
      },
      {
        "id": "04ecf2cd-6476-4cbc-b6be-de6901c7f9e0",
        "item_name": "Headphones",
        "quantity": 11967,
        "created_at": "2023-09-06T23:17:12.315Z",
        "updated_at": "2023-09-07T04:28:09.762Z",
        "user_id": "user_entity_pk"
      },
      {
        "id": "fd62f6df-6f15-42bf-a241-d644aa4cb145",
        "item_name": "Smartwatch",
        "quantity": 36859,
        "created_at": "2023-09-07T01:20:11.088Z",
        "updated_at": "2023-09-07T04:49:04.426Z",
        "user_id": "user_entity_pk"
      }
    ],
    "employee": [
      {
        "id": "045fe1ae-163a-413c-93c6-64bb7fc5829e",
        "name": "John Smith",
        "position": "Manager",
        "salary": 28359,
        "created_at": "2023-09-07T05:36:54.129Z",
        "updated_at": "2023-09-07T02:37:52.780Z",
        "user_id": "user_entity_pk"
      },
      {
        "id": "52fc2479-f1a8-4134-8fde-8077f3c91b0b",
        "name": "Jane Johnson",
        "position": "Supervisor",
        "salary": 27341,
        "created_at": "2023-09-06T22:42:55.923Z",
        "updated_at": "2023-09-06T12:54:06.151Z",
        "user_id": "user_entity_pk"
      },
      {
        "id": "d4809da9-d8db-43be-ab17-8770b4f07eea",
        "name": "Mike Davis",
        "position": "Engineer",
        "salary": 40377,
        "created_at": "2023-09-06T17:03:26.471Z",
        "updated_at": "2023-09-06T13:45:22.502Z",
        "user_id": "user_entity_pk"
      },
      {
        "id": "2f9d36e2-9e6d-4a0e-98cf-0c3690efeed6",
        "name": "Sarah Wilson",
        "position": "Analyst",
        "salary": 61159,
        "created_at": "2023-09-06T16:08:29.388Z",
        "updated_at": "2023-09-06T13:12:56.699Z",
        "user_id": "user_entity_pk"
      },
      {
        "id": "a47fd821-5773-4c06-b104-3e332935d86f",
        "name": "David Brown",
        "position": "Assistant",
        "salary": 12184,
        "created_at": "2023-09-06T22:56:29.239Z",
        "updated_at": "2023-09-06T21:29:30.793Z",
        "user_id": "user_entity_pk"
      }
    ],
    "document": [
      {
        "id": "fdf55367-721f-4536-851b-8da73dddd8f7",
        "name": "Contract Agreement",
        "status": "Draft",
        "created_at": "2023-09-06T17:04:59.021Z",
        "updated_at": "2023-09-06T13:42:31.385Z",
        "user_id": "user_entity_pk"
      },
      {
        "id": "d6f49fab-cdbb-4002-a969-7b58b926135b",
        "name": "Financial Report",
        "status": "Pending Approval",
        "created_at": "2023-09-06T22:13:04.996Z",
        "updated_at": "2023-09-07T03:05:02.906Z",
        "user_id": "user_entity_pk"
      },
      {
        "id": "18bf9598-f17c-4573-87ef-c96d30f986a5",
        "name": "Marketing Proposal",
        "status": "In Progress",
        "created_at": "2023-09-07T00:52:42.249Z",
        "updated_at": "2023-09-07T00:32:30.170Z",
        "user_id": "user_entity_pk"
      },
      {
        "id": "1f573e6d-47c7-4f90-ac2e-90164b5a86de",
        "name": "Meeting Minutes",
        "status": "Completed",
        "created_at": "2023-09-06T13:13:00.808Z",
        "updated_at": "2023-09-07T06:12:10.697Z",
        "user_id": "user_entity_pk"
      },
      {
        "id": "6676be99-089f-4248-9877-a109474f5427",
        "name": "Employee Handbook",
        "status": "Archived",
        "created_at": "2023-09-06T09:30:45.254Z",
        "updated_at": "2023-09-07T09:14:11.607Z",
        "user_id": "user_entity_pk"
      }
    ],
    "client": [
      {
        "id": "a80bd193-5545-47ca-85d7-06f39946fe18",
        "name": "ABC Company",
        "phone": "123-456-7890",
        "address": "789 Main Street",
        "created_at": "2023-09-07T03:08:28.837Z",
        "updated_at": "2023-09-06T12:43:01.636Z",
        "user_id": "user_entity_pk"
      },
      {
        "id": "0fc06b95-cced-421b-860a-b897dea356e4",
        "name": "XYZ Corporation",
        "phone": "987-654-3210",
        "address": "456 Elm Avenue",
        "created_at": "2023-09-06T09:40:38.536Z",
        "updated_at": "2023-09-06T14:05:26.797Z",
        "user_id": "user_entity_pk"
      },
      {
        "id": "679e4212-9937-49ec-85f2-545ed023823b",
        "name": "123 Enterprises",
        "phone": "555-123-4567",
        "address": "123 Oak Lane",
        "created_at": "2023-09-07T03:51:49.472Z",
        "updated_at": "2023-09-07T07:59:50.297Z",
        "user_id": "user_entity_pk"
      },
      {
        "id": "0c232531-33f8-4784-8a46-397bdb649254",
        "name": "Best Solutions Inc.",
        "phone": "888-999-0000",
        "address": "321 Pine Road",
        "created_at": "2023-09-06T11:29:49.469Z",
        "updated_at": "2023-09-06T10:09:26.801Z",
        "user_id": "user_entity_pk"
      },
      {
        "id": "3b3696d6-e81c-4c98-adbb-e5db3ddd4de1",
        "name": "Top Notch Services",
        "phone": "111-222-3333",
        "address": "654 Maple Drive",
        "created_at": "2023-09-06T22:19:10.769Z",
        "updated_at": "2023-09-07T06:10:33.677Z",
        "user_id": "user_entity_pk"
      }
    ],
    "roqUser": [
      {
        "reference": "d59e488f-1dcc-4f1a-b1b4-5e505dd0dff9",
        "email": "Nayeli46@gmail.com",
        "firstName": "Eldridge",
        "lastName": "Witting",
        "active": true,
        "avatarUrl": "https://cloudflare-ipfs.com/ipfs/Qmd3W5DuhgHirLHGVixi6V76LhCkZUz6pnFt5AJBiyvHye/avatar/232.jpg",
        "tenantId": null
      },
      {
        "reference": "30cbc8ca-fa70-4183-b755-85644fafab3b",
        "email": "Judy.Wolff40@yahoo.com",
        "firstName": "Oswaldo",
        "lastName": "Dibbert",
        "active": true,
        "avatarUrl": "https://avatars.githubusercontent.com/u/29161587",
        "tenantId": null
      },
      {
        "reference": "a8935a0c-f76c-4137-91fa-a602858452a8",
        "email": "Monte.Erdman@gmail.com",
        "firstName": "Magnus",
        "lastName": "Mosciski",
        "active": true,
        "avatarUrl": "https://cloudflare-ipfs.com/ipfs/Qmd3W5DuhgHirLHGVixi6V76LhCkZUz6pnFt5AJBiyvHye/avatar/566.jpg",
        "tenantId": null
      },
      {
        "reference": "71ca9b55-8327-497a-b24b-a898fd63e9e6",
        "email": "Bryana.Hermann69@yahoo.com",
        "firstName": "Moises",
        "lastName": "Daniel",
        "active": true,
        "avatarUrl": "https://avatars.githubusercontent.com/u/51580857",
        "tenantId": null
      },
      {
        "reference": "a86b6221-5fb0-434d-85a5-5020b9b6ae7a",
        "email": "Caleb12@hotmail.com",
        "firstName": "Mathilde",
        "lastName": "Dare",
        "active": true,
        "avatarUrl": "https://cloudflare-ipfs.com/ipfs/Qmd3W5DuhgHirLHGVixi6V76LhCkZUz6pnFt5AJBiyvHye/avatar/1210.jpg",
        "tenantId": null
      }
    ]
  },
  {
    "property": [
      {
        "id": "793b6210-9467-40ce-a8fe-73c143655c33",
        "name": "Sunset Villa",
        "address": "123 Main Street",
        "price": 25073,
        "status": "Available",
        "created_at": "2023-09-07T05:51:52.768Z",
        "updated_at": "2023-09-07T05:56:59.375Z",
        "user_id": "user_entity_pk"
      },
      {
        "id": "dfd11de9-f5f9-4205-b2c1-4be21f3cb925",
        "name": "Ocean View House",
        "address": "456 Elm Avenue",
        "price": 22946,
        "status": "Rented",
        "created_at": "2023-09-06T19:56:39.696Z",
        "updated_at": "2023-09-07T04:05:13.771Z",
        "user_id": "user_entity_pk"
      },
      {
        "id": "d8cfba28-b43e-4003-b74b-d98dc1283463",
        "name": "Mountain Retreat",
        "address": "789 Oak Lane",
        "price": 82591,
        "status": "Under Maintenance",
        "created_at": "2023-09-07T03:19:43.354Z",
        "updated_at": "2023-09-06T15:57:06.558Z",
        "user_id": "user_entity_pk"
      },
      {
        "id": "f96ff0d5-6c7b-4343-b592-0f1b42bbe0b5",
        "name": "City Loft",
        "address": "321 Pine Road",
        "price": 66382,
        "status": "Sold",
        "created_at": "2023-09-07T06:01:49.901Z",
        "updated_at": "2023-09-06T20:10:36.717Z",
        "user_id": "user_entity_pk"
      },
      {
        "id": "a30e2054-872e-4e31-9fa8-3e5f35bb7821",
        "name": "Lakefront Cottage",
        "address": "654 Cedar Drive",
        "price": 60471,
        "status": "Vacant",
        "created_at": "2023-09-07T08:32:53.674Z",
        "updated_at": "2023-09-06T12:19:00.450Z",
        "user_id": "user_entity_pk"
      }
    ],
    "inventory": [
      {
        "id": "d41e1de0-ee6c-4b60-881a-1cccad941503",
        "item_name": "Laptop",
        "quantity": 43951,
        "created_at": "2023-09-06T16:02:02.926Z",
        "updated_at": "2023-09-06T15:29:43.801Z",
        "user_id": "user_entity_pk"
      },
      {
        "id": "e525116e-fa58-476a-8ff7-19fc625c32a3",
        "item_name": "Smartphone",
        "quantity": 91914,
        "created_at": "2023-09-06T12:12:30.161Z",
        "updated_at": "2023-09-06T09:27:56.906Z",
        "user_id": "user_entity_pk"
      },
      {
        "id": "cf98801e-92af-4848-8915-90670e92fcb1",
        "item_name": "Camera",
        "quantity": 62523,
        "created_at": "2023-09-06T19:52:04.619Z",
        "updated_at": "2023-09-06T21:16:45.246Z",
        "user_id": "user_entity_pk"
      },
      {
        "id": "aa0a6fef-9fa8-4f3f-ad34-45703db08f15",
        "item_name": "Headphones",
        "quantity": 44109,
        "created_at": "2023-09-07T00:17:50.867Z",
        "updated_at": "2023-09-06T12:56:43.867Z",
        "user_id": "user_entity_pk"
      },
      {
        "id": "0cd08948-e2ce-4227-a99c-fb22967b589d",
        "item_name": "Tablet",
        "quantity": 34687,
        "created_at": "2023-09-06T10:35:45.849Z",
        "updated_at": "2023-09-07T03:26:04.583Z",
        "user_id": "user_entity_pk"
      }
    ],
    "employee": [
      {
        "id": "67939c08-446e-4a68-a93a-c1366c773954",
        "name": "John Smith",
        "position": "Manager",
        "salary": 93676,
        "created_at": "2023-09-07T07:19:15.758Z",
        "updated_at": "2023-09-06T21:13:37.061Z",
        "user_id": "user_entity_pk"
      },
      {
        "id": "9e1df876-d646-4ab4-b8bf-aeeacfae5f68",
        "name": "Jane Doe",
        "position": "Sales Representative",
        "salary": 40311,
        "created_at": "2023-09-07T00:02:06.711Z",
        "updated_at": "2023-09-07T02:12:14.434Z",
        "user_id": "user_entity_pk"
      },
      {
        "id": "a22610c1-16ab-4c3b-9cc5-18d3ab6886b9",
        "name": "Michael Brown",
        "position": "Software Engineer",
        "salary": 45640,
        "created_at": "2023-09-06T23:18:55.067Z",
        "updated_at": "2023-09-06T19:03:28.322Z",
        "user_id": "user_entity_pk"
      },
      {
        "id": "b86ba886-b4c8-4bfa-aae7-afcdd76a3b28",
        "name": "Sarah Jones",
        "position": "HR Coordinator",
        "salary": 62255,
        "created_at": "2023-09-07T06:16:41.242Z",
        "updated_at": "2023-09-06T17:55:56.650Z",
        "user_id": "user_entity_pk"
      },
      {
        "id": "959fd958-62c4-4862-a486-e9e0eca60153",
        "name": "David Wilson",
        "position": "Marketing Specialist",
        "salary": 70750,
        "created_at": "2023-09-06T14:21:12.276Z",
        "updated_at": "2023-09-07T09:20:46.238Z",
        "user_id": "user_entity_pk"
      }
    ],
    "document": [
      {
        "id": "5ca700e9-ea2d-4d9c-9035-cc9170c5740a",
        "name": "Contract Agreement",
        "status": "Draft",
        "created_at": "2023-09-06T16:34:54.123Z",
        "updated_at": "2023-09-06T23:02:10.930Z",
        "user_id": "user_entity_pk"
      },
      {
        "id": "4474b151-6a7c-4ed7-95a3-c2a2d4a02d46",
        "name": "Financial Report",
        "status": "Pending Approval",
        "created_at": "2023-09-06T13:25:59.947Z",
        "updated_at": "2023-09-06T11:21:00.684Z",
        "user_id": "user_entity_pk"
      },
      {
        "id": "d3c5bf55-9946-4da8-96b4-918fa24436d7",
        "name": "Meeting Minutes",
        "status": "Approved",
        "created_at": "2023-09-06T10:48:45.015Z",
        "updated_at": "2023-09-06T21:58:18.818Z",
        "user_id": "user_entity_pk"
      },
      {
        "id": "fd65c2ea-8223-45e8-b0a1-8ca603414f7b",
        "name": "Product Catalog",
        "status": "Archived",
        "created_at": "2023-09-07T00:16:24.879Z",
        "updated_at": "2023-09-07T08:55:31.922Z",
        "user_id": "user_entity_pk"
      },
      {
        "id": "d3b8db97-8b39-4a1d-a171-ba022702b6c9",
        "name": "Training Manual",
        "status": "Finalized",
        "created_at": "2023-09-06T20:55:19.145Z",
        "updated_at": "2023-09-06T20:56:34.822Z",
        "user_id": "user_entity_pk"
      }
    ],
    "client": [
      {
        "id": "b6558bbc-66e3-4051-bee2-5461fd988f0d",
        "name": "ABC Company",
        "phone": "123-456-7890",
        "address": "456 Main Street",
        "created_at": "2023-09-07T02:12:38.474Z",
        "updated_at": "2023-09-07T08:11:23.314Z",
        "user_id": "user_entity_pk"
      },
      {
        "id": "315dbbea-950a-489a-951c-817d9b585a53",
        "name": "XYZ Corporation",
        "phone": "555-123-4567",
        "address": "789 Elm Avenue",
        "created_at": "2023-09-07T03:57:03.635Z",
        "updated_at": "2023-09-07T07:48:40.572Z",
        "user_id": "user_entity_pk"
      },
      {
        "id": "dddb7595-80bc-4aeb-98b1-e89432e65c94",
        "name": "123 Industries",
        "phone": "987-654-3210",
        "address": "321 Oak Lane",
        "created_at": "2023-09-06T23:45:39.723Z",
        "updated_at": "2023-09-07T00:54:27.076Z",
        "user_id": "user_entity_pk"
      },
      {
        "id": "3016953e-a645-4def-b382-495e3bd98f83",
        "name": "Acme Corporation",
        "phone": "888-555-1234",
        "address": "654 Pine Road",
        "created_at": "2023-09-07T02:09:51.617Z",
        "updated_at": "2023-09-06T13:10:12.587Z",
        "user_id": "user_entity_pk"
      },
      {
        "id": "a6391fb1-81eb-41aa-9423-2e21d0fd2027",
        "name": "Global Solutions",
        "phone": "999-888-7777",
        "address": "987 Cedar Drive",
        "created_at": "2023-09-07T01:30:38.243Z",
        "updated_at": "2023-09-07T08:26:33.629Z",
        "user_id": "user_entity_pk"
      }
    ],
    "roqUser": [
      {
        "reference": "f98b090a-151e-439f-9a92-171cff6bb4c8",
        "email": "Arden_Ward54@yahoo.com",
        "firstName": "Monroe",
        "lastName": "Hermann",
        "active": true,
        "avatarUrl": "https://avatars.githubusercontent.com/u/34022628",
        "tenantId": null
      },
      {
        "reference": "313b9b11-fe50-4d32-9e58-d2613a13eaa0",
        "email": "Freeman.Raynor99@yahoo.com",
        "firstName": "Nicole",
        "lastName": "Swaniawski",
        "active": true,
        "avatarUrl": "https://avatars.githubusercontent.com/u/7613103",
        "tenantId": null
      },
      {
        "reference": "48bdba32-10a2-49b3-88c3-5bdcf1842c9f",
        "email": "Tobin.Okuneva41@hotmail.com",
        "firstName": "Scarlett",
        "lastName": "Waelchi",
        "active": true,
        "avatarUrl": "https://cloudflare-ipfs.com/ipfs/Qmd3W5DuhgHirLHGVixi6V76LhCkZUz6pnFt5AJBiyvHye/avatar/975.jpg",
        "tenantId": null
      },
      {
        "reference": "be709898-fe7a-4987-9bd5-5ddabf5d1346",
        "email": "Kari46@yahoo.com",
        "firstName": "Pierce",
        "lastName": "Johnson-Heathcote",
        "active": true,
        "avatarUrl": "https://avatars.githubusercontent.com/u/43380873",
        "tenantId": null
      },
      {
        "reference": "8045723e-b755-44af-828b-c17696de0a0e",
        "email": "Leonor.Kunze@gmail.com",
        "firstName": "Pierre",
        "lastName": "Tillman-Stroman",
        "active": true,
        "avatarUrl": "https://avatars.githubusercontent.com/u/47328699",
        "tenantId": null
      }
    ]
  },
  {
    "property": [
      {
        "id": "13e13346-cdc1-4391-bb48-141ecd4fca1f",
        "name": "Cozy Cottage",
        "address": "123 Main Street",
        "price": 31261,
        "status": "Available",
        "created_at": "2023-09-06T17:03:28.770Z",
        "updated_at": "2023-09-07T06:49:57.830Z",
        "user_id": "user_entity_pk"
      },
      {
        "id": "08986791-ae65-474f-bdc3-016deaa4e142",
        "name": "Modern Loft",
        "address": "456 Elm Avenue",
        "price": 87276,
        "status": "Booked",
        "created_at": "2023-09-07T05:59:06.398Z",
        "updated_at": "2023-09-07T01:31:36.205Z",
        "user_id": "user_entity_pk"
      },
      {
        "id": "e559d20b-06c5-44c4-ae24-c93044d5e1b7",
        "name": "Rustic Cabin",
        "address": "789 Oak Lane",
        "price": 59499,
        "status": "Under Maintenance",
        "created_at": "2023-09-06T13:09:01.573Z",
        "updated_at": "2023-09-07T05:15:23.779Z",
        "user_id": "user_entity_pk"
      },
      {
        "id": "97fa5fc6-4860-424e-862b-1272f8f31a65",
        "name": "Luxury Villa",
        "address": "321 Pine Road",
        "price": 20903,
        "status": "Sold",
        "created_at": "2023-09-07T08:56:35.181Z",
        "updated_at": "2023-09-06T19:15:02.785Z",
        "user_id": "user_entity_pk"
      },
      {
        "id": "c922ed76-ab0e-45a2-be74-7918d7ea641c",
        "name": "Beach House",
        "address": "654 Cedar Court",
        "price": 87882,
        "status": "Pending",
        "created_at": "2023-09-07T07:03:09.073Z",
        "updated_at": "2023-09-06T12:06:55.779Z",
        "user_id": "user_entity_pk"
      }
    ],
    "inventory": [
      {
        "id": "fafe7460-0ae0-4e9a-975b-fd75a7e6e9eb",
        "item_name": "Laptop",
        "quantity": 52003,
        "created_at": "2023-09-07T08:24:42.629Z",
        "updated_at": "2023-09-07T05:08:37.921Z",
        "user_id": "user_entity_pk"
      },
      {
        "id": "198ec4ac-2a1a-461a-a1dd-7995849e5267",
        "item_name": "Smartphone",
        "quantity": 26926,
        "created_at": "2023-09-07T07:30:10.523Z",
        "updated_at": "2023-09-07T06:06:27.128Z",
        "user_id": "user_entity_pk"
      },
      {
        "id": "1b2dcfb7-3f1f-46c0-90df-a3d077d2b1aa",
        "item_name": "Camera",
        "quantity": 71038,
        "created_at": "2023-09-06T17:56:50.109Z",
        "updated_at": "2023-09-06T09:43:02.765Z",
        "user_id": "user_entity_pk"
      },
      {
        "id": "9c895bc9-8057-415a-a35e-603356f770f3",
        "item_name": "Headphones",
        "quantity": 45889,
        "created_at": "2023-09-06T13:36:17.020Z",
        "updated_at": "2023-09-07T04:21:45.446Z",
        "user_id": "user_entity_pk"
      },
      {
        "id": "9e3495fd-931e-4c51-8280-f25281e9f814",
        "item_name": "Drone",
        "quantity": 58504,
        "created_at": "2023-09-06T23:47:21.663Z",
        "updated_at": "2023-09-06T17:54:45.103Z",
        "user_id": "user_entity_pk"
      }
    ],
    "employee": [
      {
        "id": "39d9aee4-0bb3-4b18-8839-cd35d613f532",
        "name": "John Smith",
        "position": "Manager",
        "salary": 5374,
        "created_at": "2023-09-07T07:37:05.740Z",
        "updated_at": "2023-09-06T23:07:04.971Z",
        "user_id": "user_entity_pk"
      },
      {
        "id": "bf83e7c2-996e-43d0-9034-e6249ba138d4",
        "name": "Emily Johnson",
        "position": "Engineer",
        "salary": 13819,
        "created_at": "2023-09-06T12:00:34.460Z",
        "updated_at": "2023-09-06T16:27:49.069Z",
        "user_id": "user_entity_pk"
      },
      {
        "id": "7d3949d4-b34e-4e4e-acbc-953f59752ec6",
        "name": "Michael Brown",
        "position": "Sales Representative",
        "salary": 70495,
        "created_at": "2023-09-06T16:18:50.199Z",
        "updated_at": "2023-09-07T01:45:23.672Z",
        "user_id": "user_entity_pk"
      },
      {
        "id": "751bc9ce-39f5-441a-ba9a-7fbd2121e8c9",
        "name": "Sarah Davis",
        "position": "Accountant",
        "salary": 92385,
        "created_at": "2023-09-07T03:21:01.852Z",
        "updated_at": "2023-09-06T18:25:43.834Z",
        "user_id": "user_entity_pk"
      },
      {
        "id": "bf59da88-766e-4f92-afaa-0531c85b8aaf",
        "name": "David Wilson",
        "position": "Human Resources",
        "salary": 92783,
        "created_at": "2023-09-07T03:15:38.172Z",
        "updated_at": "2023-09-06T15:27:33.148Z",
        "user_id": "user_entity_pk"
      }
    ],
    "document": [
      {
        "id": "ebde3fe1-4123-43f3-a60a-59b7ff15427d",
        "name": "Contract Agreement",
        "status": "Draft",
        "created_at": "2023-09-07T09:26:58.300Z",
        "updated_at": "2023-09-06T20:22:21.176Z",
        "user_id": "user_entity_pk"
      },
      {
        "id": "bbb81a6d-0842-41c3-a091-a0ca088ffe14",
        "name": "Financial Report",
        "status": "Pending Approval",
        "created_at": "2023-09-06T20:43:42.420Z",
        "updated_at": "2023-09-06T18:49:01.759Z",
        "user_id": "user_entity_pk"
      },
      {
        "id": "34e40fbd-429e-455e-b870-cdad0290e2c7",
        "name": "Marketing Proposal",
        "status": "Reviewed",
        "created_at": "2023-09-06T15:24:12.961Z",
        "updated_at": "2023-09-07T09:27:05.009Z",
        "user_id": "user_entity_pk"
      },
      {
        "id": "82eceef2-29dd-4d5d-b006-72c1eeb0794c",
        "name": "Meeting Minutes",
        "status": "Finalized",
        "created_at": "2023-09-06T20:10:40.874Z",
        "updated_at": "2023-09-06T22:39:43.259Z",
        "user_id": "user_entity_pk"
      },
      {
        "id": "4e774a17-f874-46e2-937f-730e2f545934",
        "name": "Product Manual",
        "status": "Archived",
        "created_at": "2023-09-06T17:19:28.126Z",
        "updated_at": "2023-09-07T08:51:38.196Z",
        "user_id": "user_entity_pk"
      }
    ],
    "client": [
      {
        "id": "abcfd8bd-651a-4c5e-af90-b96c2eb0a769",
        "name": "ABC Company",
        "phone": "123-456-7890",
        "address": "456 Elm Avenue",
        "created_at": "2023-09-06T23:50:32.544Z",
        "updated_at": "2023-09-06T15:14:02.563Z",
        "user_id": "user_entity_pk"
      },
      {
        "id": "704c657b-d3b6-4ea6-8ea2-b5f4d0ac25b1",
        "name": "XYZ Corporation",
        "phone": "987-654-3210",
        "address": "789 Oak Lane",
        "created_at": "2023-09-06T10:11:19.901Z",
        "updated_at": "2023-09-07T08:33:48.752Z",
        "user_id": "user_entity_pk"
      },
      {
        "id": "751ec689-937f-46be-a933-a9db3e9e4397",
        "name": "123 Industries",
        "phone": "555-123-4567",
        "address": "321 Pine Road",
        "created_at": "2023-09-07T06:21:37.857Z",
        "updated_at": "2023-09-06T15:56:13.719Z",
        "user_id": "user_entity_pk"
      },
      {
        "id": "409c33b6-812d-466e-90fc-6aa53665b052",
        "name": "Acme Ltd.",
        "phone": "888-999-0000",
        "address": "654 Cedar Court",
        "created_at": "2023-09-07T04:56:46.714Z",
        "updated_at": "2023-09-07T02:51:45.972Z",
        "user_id": "user_entity_pk"
      },
      {
        "id": "e4595b7b-3c82-4b9a-ab3c-24bb120cdb55",
        "name": "Global Enterprises",
        "phone": "777-888-9999",
        "address": "123 Main Street",
        "created_at": "2023-09-06T21:23:10.644Z",
        "updated_at": "2023-09-07T06:33:10.217Z",
        "user_id": "user_entity_pk"
      }
    ],
    "roqUser": [
      {
        "reference": "8fdae2a6-a55e-4e2d-a5b8-d4c2d98cd4a5",
        "email": "Camren_Purdy@gmail.com",
        "firstName": "Ernestina",
        "lastName": "Jakubowski-Goodwin",
        "active": true,
        "avatarUrl": "https://avatars.githubusercontent.com/u/90163972",
        "tenantId": null
      },
      {
        "reference": "d4ed2c53-e029-4f0c-8b74-04e07930cf6f",
        "email": "Chance37@hotmail.com",
        "firstName": "Breana",
        "lastName": "Dietrich",
        "active": true,
        "avatarUrl": "https://cloudflare-ipfs.com/ipfs/Qmd3W5DuhgHirLHGVixi6V76LhCkZUz6pnFt5AJBiyvHye/avatar/532.jpg",
        "tenantId": null
      },
      {
        "reference": "cc918e7a-d421-4ff0-82e7-06da09062cdc",
        "email": "Michale14@yahoo.com",
        "firstName": "Yvette",
        "lastName": "Gibson",
        "active": true,
        "avatarUrl": "https://cloudflare-ipfs.com/ipfs/Qmd3W5DuhgHirLHGVixi6V76LhCkZUz6pnFt5AJBiyvHye/avatar/891.jpg",
        "tenantId": null
      },
      {
        "reference": "397dd539-8c5a-4e3f-bd55-808ebf7cd826",
        "email": "Priscilla.Friesen67@gmail.com",
        "firstName": "Jacinthe",
        "lastName": "Nolan",
        "active": true,
        "avatarUrl": "https://avatars.githubusercontent.com/u/30781054",
        "tenantId": null
      },
      {
        "reference": "861e1e3c-4132-49aa-bc38-30345c411923",
        "email": "Arianna.Boyer95@gmail.com",
        "firstName": "Jay",
        "lastName": "Nikolaus",
        "active": true,
        "avatarUrl": "https://avatars.githubusercontent.com/u/9409046",
        "tenantId": null
      }
    ]
  },
  {
    "property": [
      {
        "id": "5be14384-3ab8-46a8-9894-d226f1082782",
        "name": "Sunset Villa",
        "address": "123 Main Street",
        "price": 76386,
        "status": "Available",
        "created_at": "2023-09-06T10:52:56.046Z",
        "updated_at": "2023-09-06T23:50:04.985Z",
        "user_id": "user_entity_pk"
      },
      {
        "id": "e8d1b842-9dd5-4299-9258-0c5be3312638",
        "name": "Ocean View House",
        "address": "456 Elm Avenue",
        "price": 4294,
        "status": "Rented",
        "created_at": "2023-09-07T02:26:02.381Z",
        "updated_at": "2023-09-06T22:44:28.888Z",
        "user_id": "user_entity_pk"
      },
      {
        "id": "3fd745e3-c351-4261-a08c-a64356e2d860",
        "name": "Mountain Retreat",
        "address": "789 Oak Drive",
        "price": 6056,
        "status": "Under Maintenance",
        "created_at": "2023-09-07T09:20:10.592Z",
        "updated_at": "2023-09-06T15:52:09.558Z",
        "user_id": "user_entity_pk"
      },
      {
        "id": "8e70c7b1-e358-4295-9e14-e84f7ec4fe1b",
        "name": "Cityscape Apartment",
        "address": "321 Pine Lane",
        "price": 22865,
        "status": "Sold",
        "created_at": "2023-09-06T11:03:03.119Z",
        "updated_at": "2023-09-07T00:30:35.987Z",
        "user_id": "user_entity_pk"
      },
      {
        "id": "e6a0f9ab-0604-4f1c-be51-2d7752bf520b",
        "name": "Lakefront Cottage",
        "address": "654 Maple Road",
        "price": 76688,
        "status": "Vacant",
        "created_at": "2023-09-06T09:37:32.735Z",
        "updated_at": "2023-09-06T21:26:25.266Z",
        "user_id": "user_entity_pk"
      }
    ],
    "inventory": [
      {
        "id": "76e944e7-6521-43b4-aed7-5eebd4eab273",
        "item_name": "Laptop",
        "quantity": 44302,
        "created_at": "2023-09-07T03:56:53.711Z",
        "updated_at": "2023-09-06T13:55:17.129Z",
        "user_id": "user_entity_pk"
      },
      {
        "id": "1fd7c91b-3548-421e-9d65-836eda5a9c9f",
        "item_name": "Smartphone",
        "quantity": 47922,
        "created_at": "2023-09-07T01:42:16.249Z",
        "updated_at": "2023-09-06T16:07:50.567Z",
        "user_id": "user_entity_pk"
      },
      {
        "id": "310bb5f1-d5f1-4701-bfa4-7fbb8935241b",
        "item_name": "Camera",
        "quantity": 24029,
        "created_at": "2023-09-06T13:00:25.927Z",
        "updated_at": "2023-09-07T03:27:24.146Z",
        "user_id": "user_entity_pk"
      },
      {
        "id": "2d62430c-1402-490e-83c7-6525075ef039",
        "item_name": "Headphones",
        "quantity": 53763,
        "created_at": "2023-09-06T15:13:08.034Z",
        "updated_at": "2023-09-06T10:16:47.151Z",
        "user_id": "user_entity_pk"
      },
      {
        "id": "c2c4cbad-9df0-4095-ab48-3d341628dd84",
        "item_name": "Tablet",
        "quantity": 7817,
        "created_at": "2023-09-06T15:04:27.116Z",
        "updated_at": "2023-09-07T05:13:53.730Z",
        "user_id": "user_entity_pk"
      }
    ],
    "employee": [
      {
        "id": "8b70ad35-acc6-4623-9aca-557ce7296ac4",
        "name": "John Smith",
        "position": "Manager",
        "salary": 21297,
        "created_at": "2023-09-06T14:56:24.330Z",
        "updated_at": "2023-09-06T18:45:06.079Z",
        "user_id": "user_entity_pk"
      },
      {
        "id": "3faabf23-07b8-41f5-bd5d-368f431322f5",
        "name": "Jane Johnson",
        "position": "Sales Representative",
        "salary": 33691,
        "created_at": "2023-09-06T18:56:09.091Z",
        "updated_at": "2023-09-06T09:31:44.234Z",
        "user_id": "user_entity_pk"
      },
      {
        "id": "c958019d-3d6a-430c-adb5-03ea500f41be",
        "name": "Michael Brown",
        "position": "Accountant",
        "salary": 7699,
        "created_at": "2023-09-06T10:41:56.289Z",
        "updated_at": "2023-09-07T06:08:34.065Z",
        "user_id": "user_entity_pk"
      },
      {
        "id": "d600c255-4e99-436f-847c-484543d29761",
        "name": "Sarah Davis",
        "position": "Human Resources Specialist",
        "salary": 28529,
        "created_at": "2023-09-06T22:07:59.731Z",
        "updated_at": "2023-09-07T04:28:04.030Z",
        "user_id": "user_entity_pk"
      },
      {
        "id": "d156067b-b842-4f39-b9fe-6a9504dabd93",
        "name": "Robert Wilson",
        "position": "IT Technician",
        "salary": 68237,
        "created_at": "2023-09-06T10:15:55.423Z",
        "updated_at": "2023-09-06T17:23:11.763Z",
        "user_id": "user_entity_pk"
      }
    ],
    "document": [
      {
        "id": "dcf090fb-0f6c-4a83-9924-912b412e52e7",
        "name": "Contract Agreement",
        "status": "Draft",
        "created_at": "2023-09-06T21:08:18.611Z",
        "updated_at": "2023-09-07T08:01:20.415Z",
        "user_id": "user_entity_pk"
      },
      {
        "id": "d0f5c94c-61b1-4fc1-8809-a1cd145bddea",
        "name": "Financial Report",
        "status": "Pending Approval",
        "created_at": "2023-09-06T11:52:44.548Z",
        "updated_at": "2023-09-06T18:15:24.688Z",
        "user_id": "user_entity_pk"
      },
      {
        "id": "7331ee5b-ad95-4da9-9d3a-f53a49018d86",
        "name": "Meeting Minutes",
        "status": "Finalized",
        "created_at": "2023-09-06T12:52:51.677Z",
        "updated_at": "2023-09-06T13:05:59.500Z",
        "user_id": "user_entity_pk"
      },
      {
        "id": "dd55b55b-e183-4111-8d4a-830465299434",
        "name": "Employee Handbook",
        "status": "Archived",
        "created_at": "2023-09-06T16:54:48.588Z",
        "updated_at": "2023-09-06T10:46:51.867Z",
        "user_id": "user_entity_pk"
      },
      {
        "id": "ede616f0-b709-445a-b729-f3092851e879",
        "name": "Product Catalog",
        "status": "Reviewed",
        "created_at": "2023-09-06T18:31:25.452Z",
        "updated_at": "2023-09-06T11:51:06.665Z",
        "user_id": "user_entity_pk"
      }
    ],
    "client": [
      {
        "id": "9845e517-748f-40cf-aec5-af18fe310f11",
        "name": "ABC Company",
        "phone": "123-456-7890",
        "address": "123 Main Street",
        "created_at": "2023-09-07T06:53:08.051Z",
        "updated_at": "2023-09-06T21:07:06.419Z",
        "user_id": "user_entity_pk"
      },
      {
        "id": "5200956d-9373-4832-9ca1-00825d1e476b",
        "name": "XYZ Corporation",
        "phone": "987-654-3210",
        "address": "456 Elm Avenue",
        "created_at": "2023-09-06T17:00:57.774Z",
        "updated_at": "2023-09-06T09:43:17.865Z",
        "user_id": "user_entity_pk"
      },
      {
        "id": "d944ca28-e7c8-41f5-98b9-75bfcf1b22cf",
        "name": "123 Enterprises",
        "phone": "555-123-4567",
        "address": "789 Oak Drive",
        "created_at": "2023-09-07T04:18:02.619Z",
        "updated_at": "2023-09-06T15:01:33.437Z",
        "user_id": "user_entity_pk"
      },
      {
        "id": "723c34e6-f605-4810-9e92-eb625aa8a7d3",
        "name": "Acme Inc.",
        "phone": "888-999-0000",
        "address": "321 Pine Lane",
        "created_at": "2023-09-06T20:10:27.333Z",
        "updated_at": "2023-09-06T20:01:21.411Z",
        "user_id": "user_entity_pk"
      },
      {
        "id": "8774015c-177b-400a-86e1-90f6aaa5af0e",
        "name": "Global Solutions",
        "phone": "777-888-9999",
        "address": "654 Maple Road",
        "created_at": "2023-09-06T15:32:43.416Z",
        "updated_at": "2023-09-06T23:10:28.851Z",
        "user_id": "user_entity_pk"
      }
    ],
    "roqUser": [
      {
        "reference": "e8efa28c-c297-4288-9b5e-c768434fb493",
        "email": "Kaya86@hotmail.com",
        "firstName": "Esmeralda",
        "lastName": "Mohr",
        "active": true,
        "avatarUrl": "https://cloudflare-ipfs.com/ipfs/Qmd3W5DuhgHirLHGVixi6V76LhCkZUz6pnFt5AJBiyvHye/avatar/178.jpg",
        "tenantId": null
      },
      {
        "reference": "3d67dba4-dad9-4112-995f-9492c317a729",
        "email": "Emilio.Auer@yahoo.com",
        "firstName": "Shakira",
        "lastName": "Collins",
        "active": true,
        "avatarUrl": "https://cloudflare-ipfs.com/ipfs/Qmd3W5DuhgHirLHGVixi6V76LhCkZUz6pnFt5AJBiyvHye/avatar/577.jpg",
        "tenantId": null
      },
      {
        "reference": "7aecf555-5dec-4e48-9ed1-3e6aeff0c7e4",
        "email": "Rosario.Langosh@hotmail.com",
        "firstName": "Delphia",
        "lastName": "MacGyver",
        "active": true,
        "avatarUrl": "https://avatars.githubusercontent.com/u/49085042",
        "tenantId": null
      },
      {
        "reference": "98a7a569-f291-4b37-82a8-2ed720684f95",
        "email": "Bernardo.Wilderman@hotmail.com",
        "firstName": "Tre",
        "lastName": "Mueller",
        "active": true,
        "avatarUrl": "https://avatars.githubusercontent.com/u/5193788",
        "tenantId": null
      },
      {
        "reference": "9d8718d9-9d6e-487b-8290-ec7272df9893",
        "email": "Adelia_Zboncak@hotmail.com",
        "firstName": "Novella",
        "lastName": "Klein",
        "active": true,
        "avatarUrl": "https://avatars.githubusercontent.com/u/18291402",
        "tenantId": null
      }
    ]
  },
  {
    "property": [
      {
        "id": "9b0e4785-edd2-41a8-a1bd-3d288c301421",
        "name": "Villa Sunshine",
        "address": "123 Main Street",
        "price": 38610,
        "status": "Available",
        "created_at": "2023-09-06T10:17:30.233Z",
        "updated_at": "2023-09-07T07:46:45.824Z",
        "user_id": "user_entity_pk"
      },
      {
        "id": "b3731378-a123-4785-8a08-9a0d46f8810e",
        "name": "Ocean View Apartment",
        "address": "456 Elm Avenue",
        "price": 11662,
        "status": "Rented",
        "created_at": "2023-09-06T18:28:58.361Z",
        "updated_at": "2023-09-06T18:37:10.165Z",
        "user_id": "user_entity_pk"
      },
      {
        "id": "8e6d03cf-52e1-4b32-b419-fac8476667f2",
        "name": "Mountain Retreat",
        "address": "789 Oak Lane",
        "price": 66109,
        "status": "Under Maintenance",
        "created_at": "2023-09-06T19:30:42.903Z",
        "updated_at": "2023-09-06T19:39:05.333Z",
        "user_id": "user_entity_pk"
      },
      {
        "id": "bcc52d41-ff08-4f91-9dc6-ec3f9ae87b9c",
        "name": "City Center Condo",
        "address": "321 Pine Road",
        "price": 57320,
        "status": "Sold",
        "created_at": "2023-09-06T12:57:39.551Z",
        "updated_at": "2023-09-07T04:50:05.445Z",
        "user_id": "user_entity_pk"
      },
      {
        "id": "3222b252-917f-433b-b67c-248f15a85168",
        "name": "Lakefront Cottage",
        "address": "654 Maple Court",
        "price": 4413,
        "status": "Vacant",
        "created_at": "2023-09-07T06:02:01.112Z",
        "updated_at": "2023-09-06T17:51:48.660Z",
        "user_id": "user_entity_pk"
      }
    ],
    "inventory": [
      {
        "id": "5a9ecc52-2125-4ea0-8ef0-5d460b96a8a2",
        "item_name": "Smartphone",
        "quantity": 94398,
        "created_at": "2023-09-06T13:09:11.024Z",
        "updated_at": "2023-09-06T20:03:47.923Z",
        "user_id": "user_entity_pk"
      },
      {
        "id": "ebba28ad-5c57-4f3b-b608-bb04e7c5ed4f",
        "item_name": "Laptop",
        "quantity": 99633,
        "created_at": "2023-09-06T22:28:59.489Z",
        "updated_at": "2023-09-06T23:49:39.346Z",
        "user_id": "user_entity_pk"
      },
      {
        "id": "ea8eccc7-84ff-4650-9899-1307d5a2db0b",
        "item_name": "Camera",
        "quantity": 54336,
        "created_at": "2023-09-06T14:41:56.108Z",
        "updated_at": "2023-09-07T06:48:44.104Z",
        "user_id": "user_entity_pk"
      },
      {
        "id": "ac628573-51cb-465b-8675-cd88b813e970",
        "item_name": "Headphones",
        "quantity": 30150,
        "created_at": "2023-09-06T17:18:11.621Z",
        "updated_at": "2023-09-07T05:58:34.478Z",
        "user_id": "user_entity_pk"
      },
      {
        "id": "52968137-7e0d-4e12-a263-4c790c67e123",
        "item_name": "Tablet",
        "quantity": 15271,
        "created_at": "2023-09-07T01:10:45.559Z",
        "updated_at": "2023-09-07T08:37:26.099Z",
        "user_id": "user_entity_pk"
      }
    ],
    "employee": [
      {
        "id": "34a4c11d-107d-4996-a3f2-62f4eca0ba63",
        "name": "John Smith",
        "position": "Manager",
        "salary": 27679,
        "created_at": "2023-09-07T04:34:51.229Z",
        "updated_at": "2023-09-06T15:44:36.267Z",
        "user_id": "user_entity_pk"
      },
      {
        "id": "c26a9838-3b1a-498d-93a5-909b0dd35319",
        "name": "Jane Johnson",
        "position": "Sales Representative",
        "salary": 85818,
        "created_at": "2023-09-07T07:45:21.889Z",
        "updated_at": "2023-09-07T06:15:07.033Z",
        "user_id": "user_entity_pk"
      },
      {
        "id": "f34b97b7-813c-462c-9d65-18f4d264bd1f",
        "name": "Michael Brown",
        "position": "Software Engineer",
        "salary": 53854,
        "created_at": "2023-09-07T03:27:03.346Z",
        "updated_at": "2023-09-07T05:33:19.010Z",
        "user_id": "user_entity_pk"
      },
      {
        "id": "6412d4f9-ddae-4aa6-9681-e5c8fb14451e",
        "name": "Sarah Davis",
        "position": "Human Resources Specialist",
        "salary": 3666,
        "created_at": "2023-09-06T17:25:42.436Z",
        "updated_at": "2023-09-06T10:10:05.986Z",
        "user_id": "user_entity_pk"
      },
      {
        "id": "181f5ba5-7043-48ab-9b23-9b1af3ef4c86",
        "name": "David Wilson",
        "position": "Accountant",
        "salary": 72569,
        "created_at": "2023-09-07T00:31:50.296Z",
        "updated_at": "2023-09-06T11:32:39.174Z",
        "user_id": "user_entity_pk"
      }
    ],
    "document": [
      {
        "id": "fc4230c7-69e0-46da-9a76-15ad21ac3d64",
        "name": "Contract Agreement",
        "status": "Draft",
        "created_at": "2023-09-07T03:49:49.751Z",
        "updated_at": "2023-09-07T00:50:32.051Z",
        "user_id": "user_entity_pk"
      },
      {
        "id": "87eb141b-13ec-4f70-b833-0281cdd7287a",
        "name": "Financial Report",
        "status": "Under Review",
        "created_at": "2023-09-06T10:36:26.776Z",
        "updated_at": "2023-09-06T11:16:19.305Z",
        "user_id": "user_entity_pk"
      },
      {
        "id": "0e3a6d30-9211-4efa-9696-5d1cf9979144",
        "name": "Meeting Minutes",
        "status": "Approved",
        "created_at": "2023-09-07T00:00:52.049Z",
        "updated_at": "2023-09-06T11:52:41.947Z",
        "user_id": "user_entity_pk"
      },
      {
        "id": "d394b2d4-bfc9-4cb0-b5b6-dc16d457c720",
        "name": "Project Proposal",
        "status": "Finalized",
        "created_at": "2023-09-07T05:49:50.205Z",
        "updated_at": "2023-09-06T14:48:43.658Z",
        "user_id": "user_entity_pk"
      },
      {
        "id": "93033101-2de5-440e-bd82-71aac801fc4d",
        "name": "Training Manual",
        "status": "Archived",
        "created_at": "2023-09-07T03:13:35.113Z",
        "updated_at": "2023-09-07T01:44:33.322Z",
        "user_id": "user_entity_pk"
      }
    ],
    "client": [
      {
        "id": "bcb90bc5-1aa7-471c-9a55-2078d13d2cbc",
        "name": "ABC Company",
        "phone": "123-456-7890",
        "address": "789 Main Street",
        "created_at": "2023-09-06T10:47:48.221Z",
        "updated_at": "2023-09-06T23:15:06.096Z",
        "user_id": "user_entity_pk"
      },
      {
        "id": "860be0a9-610b-43c9-8682-897de7b2520f",
        "name": "XYZ Corporation",
        "phone": "555-123-4567",
        "address": "456 Elm Avenue",
        "created_at": "2023-09-07T00:47:07.600Z",
        "updated_at": "2023-09-06T21:41:02.558Z",
        "user_id": "user_entity_pk"
      },
      {
        "id": "a57fc4f8-1d13-47ce-9194-6f56e384480e",
        "name": "123 Industries",
        "phone": "987-654-3210",
        "address": "123 Oak Lane",
        "created_at": "2023-09-07T08:14:26.485Z",
        "updated_at": "2023-09-07T02:46:47.168Z",
        "user_id": "user_entity_pk"
      },
      {
        "id": "b54ae6c6-8717-4500-b10c-e6ab2f7d0eeb",
        "name": "Acme Ltd.",
        "phone": "888-555-1234",
        "address": "321 Pine Road",
        "created_at": "2023-09-06T12:31:40.412Z",
        "updated_at": "2023-09-07T06:46:26.462Z",
        "user_id": "user_entity_pk"
      },
      {
        "id": "3ab0a1b0-084f-400e-80cd-2edf6ee31d5a",
        "name": "Global Solutions",
        "phone": "999-888-7777",
        "address": "654 Maple Court",
        "created_at": "2023-09-06T14:05:39.569Z",
        "updated_at": "2023-09-06T12:19:21.313Z",
        "user_id": "user_entity_pk"
      }
    ],
    "roqUser": [
      {
        "reference": "527d2c7a-b970-425b-871e-381bf01c53b1",
        "email": "Haven.Feest44@yahoo.com",
        "firstName": "Bradly",
        "lastName": "Balistreri",
        "active": true,
        "avatarUrl": "https://avatars.githubusercontent.com/u/36655533",
        "tenantId": null
      },
      {
        "reference": "f48d410d-6bbb-43ba-85b9-8555d2b531e9",
        "email": "Theresia97@gmail.com",
        "firstName": "Jameson",
        "lastName": "Kub",
        "active": true,
        "avatarUrl": "https://avatars.githubusercontent.com/u/64849093",
        "tenantId": null
      },
      {
        "reference": "f69ad82f-830c-4742-aa03-d659c8284963",
        "email": "Nicolette.Strosin@hotmail.com",
        "firstName": "Rosalia",
        "lastName": "Fahey",
        "active": true,
        "avatarUrl": "https://cloudflare-ipfs.com/ipfs/Qmd3W5DuhgHirLHGVixi6V76LhCkZUz6pnFt5AJBiyvHye/avatar/147.jpg",
        "tenantId": null
      },
      {
        "reference": "8730d7d6-6ab2-45ce-bc9d-ca45787d2ca4",
        "email": "Katharina14@yahoo.com",
        "firstName": "Bethany",
        "lastName": "Graham",
        "active": true,
        "avatarUrl": "https://avatars.githubusercontent.com/u/11182443",
        "tenantId": null
      },
      {
        "reference": "860fe283-0200-4db9-9a47-1be248474e3b",
        "email": "Maximo_Stoltenberg24@hotmail.com",
        "firstName": "Maybelle",
        "lastName": "Schumm",
        "active": true,
        "avatarUrl": "https://cloudflare-ipfs.com/ipfs/Qmd3W5DuhgHirLHGVixi6V76LhCkZUz6pnFt5AJBiyvHye/avatar/303.jpg",
        "tenantId": null
      }
    ]
  }
]
